Workbook
Name UPDATE: 'Data Sheet'!$E$1

Sheet DCF
A1: NESTLE INDIA LTD — 5-Year Discounted Cash Flow Model
A3: Case Selector (1 = Bear, 2 = Base, 3 = Bull) | B3: 2
A4: Selected Case | B4: =IF($B$3=1,"BEAR",IF($B$3=2,"BASE","BULL")) -> BASE
A6: Market Data
A7: Current Share Price | B7: ='Data Sheet'!B8 -> 1382.65
A8: Diluted Shares Outstanding (cr) | B8: ='Data Sheet'!B6 -> 192.83143
A9: Market Capitalisation | B9: =B7*B8 -> 266618.37
A10: Total Borrowings | B10: ='Historical FS'!K50 -> 444.16
A11: Cash & Bank | B11: ='Historical FS'!K62 -> 1340.87
A12: Net Debt / (Net Cash) | B12: =B10-B11 -> -896.71
A13: FY2026A Revenue | B13: ='Historical FS'!K5 -> 23154.6
A14: FY2026A EBIT | B14: ='Historical FS'!K22 -> 4607.73
A15: FY2026A EBIT Margin (%) | B15: =B14/B13 -> 0.19899847
A17: Bear Case Assumptions
A18: Assumption | B18: FY2027E | C18: FY2028E | D18: FY2029E | E18: FY2030E | F18: FY2031E
A19: Revenue Growth (%) | B19: 0.07 | C19: 0.06 | D19: 0.06 | E19: 0.05 | F19: 0.05
A20: EBIT Margin (%) | B20: 0.185 | C20: 0.183 | D20: 0.18 | E20: 0.18 | F20: 0.18
A21: Tax Rate (%) | B21: 0.255 | C21: 0.255 | D21: 0.255 | E21: 0.255 | F21: 0.255
A22: D&A (% of Revenue) | B22: 0.032 | C22: 0.032 | D22: 0.032 | E22: 0.032 | F22: 0.032
A23: Capex (% of Revenue) | B23: 0.045 | C23: 0.045 | D23: 0.045 | E23: 0.045 | F23: 0.045
A24: Δ NWC (% of Δ Revenue) | B24: -0.03 | C24: -0.03 | D24: -0.03 | E24: -0.03 | F24: -0.03
A26: Base Case Assumptions
A27: Assumption | B27: FY2027E | C27: FY2028E | D27: FY2029E | E27: FY2030E | F27: FY2031E
A28: Revenue Growth (%) | B28: 0.11 | C28: 0.1 | D28: 0.09 | E28: 0.08 | F28: 0.07
A29: EBIT Margin (%) | B29: 0.2 | C29: 0.202 | D29: 0.204 | E29: 0.206 | F29: 0.208
A30: Tax Rate (%) | B30: 0.25 | C30: 0.25 | D30: 0.25 | E30: 0.25 | F30: 0.25
A31: D&A (% of Revenue) | B31: 0.03 | C31: 0.03 | D31: 0.03 | E31: 0.03 | F31: 0.03
A32: Capex (% of Revenue) | B32: 0.036 | C32: 0.036 | D32: 0.036 | E32: 0.036 | F32: 0.036
A33: Δ NWC (% of Δ Revenue) | B33: -0.05 | C33: -0.05 | D33: -0.05 | E33: -0.05 | F33: -0.05
A35: Bull Case Assumptions
A36: Assumption | B36: FY2027E | C36: FY2028E | D36: FY2029E | E36: FY2030E | F36: FY2031E
A37: Revenue Growth (%) | B37: 0.14 | C37: 0.13 | D37: 0.12 | E37: 0.11 | F37: 0.1
A38: EBIT Margin (%) | B38: 0.21 | C38: 0.215 | D38: 0.22 | E38: 0.225 | F38: 0.23
A39: Tax Rate (%) | B39: 0.245 | C39: 0.245 | D39: 0.245 | E39: 0.245 | F39: 0.245
A40: D&A (% of Revenue) | B40: 0.029 | C40: 0.029 | D40: 0.029 | E40: 0.029 | F40: 0.029
A41: Capex (% of Revenue) | B41: 0.034 | C41: 0.034 | D41: 0.034 | E41: 0.034 | F41: 0.034
A42: Δ NWC (% of Δ Revenue) | B42: -0.06 | C42: -0.06 | D42: -0.06 | E42: -0.06 | F42: -0.06
A44: Selected Case
A45: Assumption | B45: FY2027E | C45: FY2028E | D45: FY2029E | E45: FY2030E | F45: FY2031E
A46: Revenue Growth (%) | B46: =CHOOSE($B$3,B19,B28,B37) -> 0.11 | C46: =CHOOSE($B$3,C19,C28,C37) -> 0.1 | D46: =CHOOSE($B$3,D19,D28,D37) -> 0.09 | E46: =CHOOSE($B$3,E19,E28,E37) -> 0.08 | F46: =CHOOSE($B$3,F19,F28,F37) -> 0.07
A47: EBIT Margin (%) | B47: =CHOOSE($B$3,B20,B29,B38) -> 0.2 | C47: =CHOOSE($B$3,C20,C29,C38) -> 0.202 | D47: =CHOOSE($B$3,D20,D29,D38) -> 0.204 | E47: =CHOOSE($B$3,E20,E29,E38) -> 0.206 | F47: =CHOOSE($B$3,F20,F29,F38) -> 0.208
A48: Tax Rate (%) | B48: =CHOOSE($B$3,B21,B30,B39) -> 0.25 | C48: =CHOOSE($B$3,C21,C30,C39) -> 0.25 | D48: =CHOOSE($B$3,D21,D30,D39) -> 0.25 | E48: =CHOOSE($B$3,E21,E30,E39) -> 0.25 | F48: =CHOOSE($B$3,F21,F30,F39) -> 0.25
A49: D&A (% of Revenue) | B49: =CHOOSE($B$3,B22,B31,B40) -> 0.03 | C49: =CHOOSE($B$3,C22,C31,C40) -> 0.03 | D49: =CHOOSE($B$3,D22,D31,D40) -> 0.03 | E49: =CHOOSE($B$3,E22,E31,E40) -> 0.03 | F49: =CHOOSE($B$3,F22,F31,F40) -> 0.03
A50: Capex (% of Revenue) | B50: =CHOOSE($B$3,B23,B32,B41) -> 0.036 | C50: =CHOOSE($B$3,C23,C32,C41) -> 0.036 | D50: =CHOOSE($B$3,D23,D32,D41) -> 0.036 | E50: =CHOOSE($B$3,E23,E32,E41) -> 0.036 | F50: =CHOOSE($B$3,F23,F32,F41) -> 0.036
A51: Δ NWC (% of Δ Revenue) | B51: =CHOOSE($B$3,B24,B33,B42) -> -0.05 | C51: =CHOOSE($B$3,C24,C33,C42) -> -0.05 | D51: =CHOOSE($B$3,D24,D33,D42) -> -0.05 | E51: =CHOOSE($B$3,E24,E33,E42) -> -0.05 | F51: =CHOOSE($B$3,F24,F33,F42) -> -0.05
A53: Projected Financials & Unlevered Free Cash Flow
A54: Fiscal Year | B54: FY2026A | C54: FY2027E | D54: FY2028E | E54: FY2029E | F54: FY2030E | G54: FY2031E
A55: Revenue | B55: =B13 -> 23154.6 | C55: =B55*(1+B$46) -> 25701.606 | D55: =C55*(1+C$46) -> 28271.767 | E55: =D55*(1+D$46) -> 30816.226 | F55: =E55*(1+E$46) -> 33281.524 | G55: =F55*(1+F$46) -> 35611.23
A56: % growth | B56: ='Historical FS'!K6 -> 0.14617881 | C56: =C55/B55-1 -> 0.11 | D56: =D55/C55-1 -> 0.1 | E56: =E55/D55-1 -> 0.09 | F56: =F55/E55-1 -> 0.08 | G56: =G55/F55-1 -> 0.07
A57: EBIT | B57: =B14 -> 4607.73 | C57: =C55*B$47 -> 5140.3212 | D57: =D55*C$47 -> 5710.8969 | E57: =E55*D$47 -> 6286.51 | F57: =F55*E$47 -> 6855.9939 | G57: =G55*F$47 -> 7407.1359
A58: EBIT margin | B58: =B57/B55 -> 0.19899847 | C58: =C57/C55 -> 0.2 | D58: =D57/D55 -> 0.202 | E58: =E57/E55 -> 0.204 | F58: =F57/F55 -> 0.206 | G58: =G57/G55 -> 0.208
A59: Less: Taxes on EBIT | C59: =C57*B$48 -> 1285.0803 | D59: =D57*C$48 -> 1427.7242 | E59: =E57*D$48 -> 1571.6275 | F59: =F57*E$48 -> 1713.9985 | G59: =G57*F$48 -> 1851.784
A60: NOPAT | C60: =C57-C59 -> 3855.2409 | D60: =D57-D59 -> 4283.1726 | E60: =E57-E59 -> 4714.8825 | F60: =F57-F59 -> 5141.9954 | G60: =G57-G59 -> 5555.3519
A61: (+) Depreciation & Amortisation | C61: =C55*B$49 -> 771.04818 | D61: =D55*C$49 -> 848.153 | E61: =E55*D$49 -> 924.48677 | F61: =F55*E$49 -> 998.44571 | G61: =G55*F$49 -> 1068.3369
A62: (-) Capital Expenditure | C62: =C55*B$50 -> 925.25782 | D62: =D55*C$50 -> 1017.7836 | E62: =E55*D$50 -> 1109.3841 | F62: =F55*E$50 -> 1198.1349 | G62: =G55*F$50 -> 1282.0043
A63: (-) Increase / (Decrease) in NWC | C63: =(C55-B55)*B$51 -> -127.3503 | D63: =(D55-C55)*C$51 -> -128.50803 | E63: =(E55-D55)*D$51 -> -127.22295 | F63: =(F55-E55)*E$51 -> -123.2649 | G63: =(G55-F55)*F$51 -> -116.48533
A64: Unlevered Free Cash Flow | C64: =C60+C61-C62-C63 -> 3828.3816 | D64: =D60+D61-D62-D63 -> 4242.0501 | E64: =E60+E61-E62-E63 -> 4657.2081 | F64: =F60+F61-F62-F63 -> 5065.5712 | G64: =G60+G61-G62-G63 -> 5458.1699
A65: FCF % of Revenue | C65: =C64/C55 -> 0.14895495 | D65: =D64/D55 -> 0.15004545 | E65: =E64/E55 -> 0.15112844 | F65: =F64/F55 -> 0.1522037 | G65: =G64/G55 -> 0.15327103
A67: Discounting
A68: Fiscal Year | C68: FY2027E | D68: FY2028E | E68: FY2029E | F68: FY2030E | G68: FY2031E
A69: Unlevered Free Cash Flow | C69: =C64 -> 3828.3816 | D69: =D64 -> 4242.0501 | E69: =E64 -> 4657.2081 | F69: =F64 -> 5065.5712 | G69: =G64 -> 5458.1699
A70: Discount Period (years) | C70: 1 | D70: 2 | E70: 3 | F70: 4 | G70: 5
A71: Discount Factor | C71: =1/(1+$B$75)^C70 -> 0.90259719 | D71: =1/(1+$B$75)^D70 -> 0.81468168 | E71: =1/(1+$B$75)^E70 -> 0.7353294 | F71: =1/(1+$B$75)^F70 -> 0.66370624 | G71: =1/(1+$B$75)^G70 -> 0.59905939
A72: PV of Free Cash Flow | C72: =C69*C71 -> 3455.4864 | D72: =D69*D71 -> 3455.9205 | E72: =E69*E71 -> 3424.582 | F72: =F69*F71 -> 3362.0512 | G72: =G69*G71 -> 3269.7679
A74: Terminal Value (Perpetuity Growth)
A75: WACC | B75: =B93 -> 0.10791393
A76: Terminal Growth Rate (g) | B76: 0.05
A77: Terminal Year FCF (FY2031E × (1+g)) | B77: =G64*(1+B76) -> 5731.0784
A78: Terminal Value | B78: =B77/(B75-B76) -> 98958.542
A79: PV of Terminal Value | B79: =B78/(1+B75)^G70 -> 59282.044
A81: Implied Share Price
A82: Sum of PV of FCFs | B82: =SUM(C72:G72) -> 16967.808
A83: PV of Terminal Value | B83: =B79 -> 59282.044
A84: Enterprise Value | B84: =B82+B83 -> 76249.852
A85: Less: Net Debt / (Add: Net Cash) | B85: =B12 -> -896.71
A86: Equity Value | B86: =B84-B85 -> 77146.562
A87: Diluted Shares Outstanding (cr) | B87: =B8 -> 192.83143
A88: Implied Value Per Share | B88: =B86/B87 -> 400.07256
A89: Current Share Price | B89: =B7 -> 1382.65
A90: Implied Upside / (Downside) | B90: =B88/B89-1 -> -0.71064799
A91: Check: Terminal Value % of Enterprise Value | B91: =B83/B84 -> 0.77747094
A93: WACC | B93: 0.10791393
A94: Terminal Growth Rate (g) | B94: 0.05
A96: Sensitivity Analysis — WACC Vs. Terminal Growth Rate
A97: =B88 -> 400.07256 | B97: 0.04 | C97: 0.045 | D97: 0.05 | E97: 0.055 | F97: 0.06
A98: 0.097913933 | B98: 413.67809 | C98: 445.46242 | D98: 483.88037 | E98: 531.25064 | F98: 591.11508
A99: 0.10291393 | B99: 380.54926 | C99: 406.80008 | D99: 438.01194 | E99: 475.73795 | F99: 522.25505
A100: 0.10791393 | B100: 352.30828 | C100: 374.29242 | D100: 400.07256 | E100: 430.72479 | F100: 467.77437
A101: 0.11291393 | B101: 327.94941 | C101: 346.57987 | D101: 368.17158 | E101: 393.49155 | F101: 423.59663
A102: 0.11791393 | B102: 306.72507 | C102: 322.67578 | D102: 340.97516 | E102: 362.18318 | F102: 387.05318

Sheet WACC
A1: Weighted Average Cost of Capital
A3: Cost Of Equity (CAPM)
A4: Risk-Free Rate (10Y India G-Sec) | B4: 0.066
A5: Beta (levered vs Nifty) | B5: 0.6
A6: Equity Risk Premium (India) | B6: 0.07
A7: Cost Of Equity | B7: =B4+B5*B6 -> 0.108
A9: Cost Of Debt
A10: Interest Expense FY2026A | B10: ='Historical FS'!K25 -> 158.31
A11: Average Borrowings | B11: =AVERAGE('Historical FS'!J50:K50) -> 805.505
A12: Implied Interest Cost | B12: =B10/B11 -> 0.19653509
A13: Pre-Tax Cost of Debt (assumed) | B13: 0.075
A14: Tax Rate | B14: =DCF!B48 -> 0.25
A15: After-Tax Cost Of Debt | B15: =B13*(1-B14) -> 0.05625
A17: Capital Structure (Market Values)
A18: Current Share Price | B18: =DCF!B7 -> 1382.65
A19: Diluted Shares Outstanding (cr) | B19: =DCF!B8 -> 192.83143
A20: Market Capitalisation | B20: =B18*B19 -> 266618.37
A21: Total Borrowings | B21: =DCF!B10 -> 444.16
A22: Cash & Bank | B22: =DCF!B11 -> 1340.87
A23: Net Debt / (Net Cash) | B23: =B21-B22 -> -896.71
A24: Total Capitalisation | B24: =B20+B21 -> 267062.53
A26: WACC Calculation
A27: Component | B27: Weight | C27: Cost | D27: Contribution
A28: Equity | B28: =B20/$B$24 -> 0.99833687 | C28: =B7 -> 0.108 | D28: =B28*C28 -> 0.10782038
A29: Debt | B29: =B21/$B$24 -> 0.0016631311 | C29: =B15 -> 0.05625 | D29: =B29*C29 -> 9.3551125e-05
A30: Weighted Average Cost Of Capital | B30: =SUM(D28:D29) -> 0.10791393

Sheet Working Capital
A2: Working Capital
A3: Fiscal Year | B3: FY2018 | C3: FY2019 | D3: FY2020 | E3: FY2021 | F3: FY2022 | G3: FY2026
A4: Sales | B4: ='Profit & Loss'!C4 -> 11292.27 | C4: ='Profit & Loss'!D4 -> 12368.9 | D4: ='Profit & Loss'!E4 -> 13350.03 | E4: ='Profit & Loss'!F4 -> 14740.59 | F4: ='Profit & Loss'!G4 -> 16896.96 | G4: ='Profit & Loss'!K4 -> 23154.6
A5: Δ Sales | B5: ='Profit & Loss'!C4-'Profit & Loss'!B4 -> 1282.67 | C5: ='Profit & Loss'!D4-'Profit & Loss'!C4 -> 1076.63 | D5: ='Profit & Loss'!E4-'Profit & Loss'!D4 -> 981.13 | E5: ='Profit & Loss'!F4-'Profit & Loss'!E4 -> 1390.56 | F5: ='Profit & Loss'!G4-'Profit & Loss'!F4 -> 2156.37 | G5: ='Profit & Loss'!K4-'Profit & Loss'!J4 -> 2953.04
A6: Working capital | B6: ='Balance Sheet'!C16 -> -1455.43 | C6: ='Balance Sheet'!D16 -> -2127.99 | D6: ='Balance Sheet'!E16 -> -2114.93 | E6: ='Balance Sheet'!F16 -> -1802.04 | F6: ='Balance Sheet'!G16 -> -1449.91 | G6: ='Balance Sheet'!K16 -> -1749.6
A7: Δ Working capital | B7: ='Balance Sheet'!C16-'Balance Sheet'!B16 -> -221.95 | C7: ='Balance Sheet'!D16-'Balance Sheet'!C16 -> -672.56 | D7: ='Balance Sheet'!E16-'Balance Sheet'!D16 -> 13.06 | E7: ='Balance Sheet'!F16-'Balance Sheet'!E16 -> 312.89 | F7: ='Balance Sheet'!G16-'Balance Sheet'!F16 -> 352.13 | G7: ='Balance Sheet'!K16-'Balance Sheet'!J16 -> 318.17
A8: Δ NWC ÷ Δ Sales | B8: =B7/B5 -> -0.17303749 | C8: =C7/C5 -> -0.62469 | D8: =D7/D5 -> 0.013311182 | E8: =E7/E5 -> 0.22501007 | F8: =F7/F5 -> 0.16329758 | G8: =G7/G5 -> 0.10774321
A10: Average of the six years | B10: =AVERAGE(B8:G8) -> -0.04806091

Sheet Capex
A2: Capex
A3: Fiscal Year | B3: FY2018 | C3: FY2019 | D3: FY2020 | E3: FY2021 | F3: FY2022 | G3: FY2025 | H3: FY2026
A4: Net block | B4: ='Balance Sheet'!C10 -> 2400.62 | C4: ='Balance Sheet'!D10 -> 2341.45 | D4: ='Balance Sheet'!E10 -> 2179.41 | E4: ='Balance Sheet'!F10 -> 2994.67 | F4: ='Balance Sheet'!G10 -> 3043.7 | G4: ='Balance Sheet'!J10 -> 5473.61 | H4: ='Balance Sheet'!K10 -> 6290.42
A5: Δ Net block | B5: ='Balance Sheet'!C10-'Balance Sheet'!B10 -> -215.56 | C5: ='Balance Sheet'!D10-'Balance Sheet'!C10 -> -59.17 | D5: ='Balance Sheet'!E10-'Balance Sheet'!D10 -> -162.04 | E5: ='Balance Sheet'!F10-'Balance Sheet'!E10 -> 815.26 | F5: ='Balance Sheet'!G10-'Balance Sheet'!F10 -> 49.03 | G5: ='Balance Sheet'!J10-'Balance Sheet'!I10 -> 2013.36 | H5: ='Balance Sheet'!K10-'Balance Sheet'!J10 -> 816.81
A6: Capital work in progress | B6: ='Balance Sheet'!C11 -> 105.2 | C6: ='Balance Sheet'!D11 -> 143.3 | D6: ='Balance Sheet'!E11 -> 638.58 | E6: ='Balance Sheet'!F11 -> 246.23 | F6: ='Balance Sheet'!G11 -> 358.36 | G6: ='Balance Sheet'!J11 -> 1172.56 | H6: ='Balance Sheet'!K11 -> 506.98
A7: Δ CWIP | B7: ='Balance Sheet'!C11-'Balance Sheet'!B11 -> 11.04 | C7: ='Balance Sheet'!D11-'Balance Sheet'!C11 -> 38.1 | D7: ='Balance Sheet'!E11-'Balance Sheet'!D11 -> 495.28 | E7: ='Balance Sheet'!F11-'Balance Sheet'!E11 -> -392.35 | F7: ='Balance Sheet'!G11-'Balance Sheet'!F11 -> 112.13 | G7: ='Balance Sheet'!J11-'Balance Sheet'!I11 -> -569.15 | H7: ='Balance Sheet'!K11-'Balance Sheet'!J11 -> -665.58
A8: Depreciation | B8: ='Profit & Loss'!C8 -> 335.67 | C8: ='Profit & Loss'!D8 -> 370.15 | D8: ='Profit & Loss'!E8 -> 370.38 | E8: ='Profit & Loss'!F8 -> 391.02 | F8: ='Profit & Loss'!G8 -> 403.01 | G8: ='Profit & Loss'!J8 -> 539.92 | H8: ='Profit & Loss'!K8 -> 699.23
A9: Capex | B9: =B5+B7+B8 -> 131.15 | C9: =C5+C7+C8 -> 349.08 | D9: =D5+D7+D8 -> 703.62 | E9: =E5+E7+E8 -> 813.93 | F9: =F5+F7+F8 -> 564.17 | G9: =G5+G7+G8 -> 1984.13 | H9: =H5+H7+H8 -> 850.46
A10: Sales | B10: ='Profit & Loss'!C4 -> 11292.27 | C10: ='Profit & Loss'!D4 -> 12368.9 | D10: ='Profit & Loss'!E4 -> 13350.03 | E10: ='Profit & Loss'!F4 -> 14740.59 | F10: ='Profit & Loss'!G4 -> 16896.96 | G10: ='Profit & Loss'!J4 -> 20201.56 | H10: ='Profit & Loss'!K4 -> 23154.6
A11: Capex ÷ Sales | B11: =B9/B10 -> 0.01161414 | C11: =C9/C10 -> 0.028222396 | D11: =D9/D10 -> 0.0527055 | E11: =E9/E10 -> 0.055216921 | F11: =F9/F10 -> 0.033388846 | G11: =G9/G10 -> 0.098216672 | H11: =H9/H10 -> 0.036729635
A13: Average Of The Seven Years | B13: =AVERAGE(B11:H11) -> 0.045156301
A14: Average Excluding FY2025 | B14: =AVERAGE(B11:F11,H11) -> 0.036312906
A15: Base Case Assumption Used | B15: =DCF!B32 -> 0.036

Sheet Historical FS
B2: ="Historical Financial Statement - "&'Data Sheet'!B1 -> Historical Financial Statement - NESTLE INDIA LTD
B3: Years | C3: ='Data Sheet'!C16 -> 43465 | D3: ='Data Sheet'!D16 -> 43830 | E3: ='Data Sheet'!E16 -> 44196 | F3: ='Data Sheet'!F16 -> 44561 | G3: ='Data Sheet'!G16 -> 44926 | H3: ='Data Sheet'!H16 -> 45291 | I3: ='Data Sheet'!I16 -> 45382 | J3: ='Data Sheet'!J16 -> 45747 | K3: ='Data Sheet'!K16 -> 46112
A4: # | B4: Income Statement
B5: Sales | C5: =IFERROR('Data Sheet'!C17,0) -> 11292.27 | D5: =IFERROR('Data Sheet'!D17,0) -> 12368.9 | E5: =IFERROR('Data Sheet'!E17,0) -> 13350.03 | F5: =IFERROR('Data Sheet'!F17,0) -> 14740.59 | G5: =IFERROR('Data Sheet'!G17,0) -> 16896.96 | H5: =IFERROR('Data Sheet'!H17,0) -> 19126.3 | I5: =IFERROR('Data Sheet'!I17,0) -> 24393.89 | J5: =IFERROR('Data Sheet'!J17,0) -> 20201.56 | K5: =IFERROR('Data Sheet'!K17,0) -> 23154.6
B6: Sales Growth | C6: - | D6: =IFERROR(D5/C5-1,0) -> 0.095342212 | E6: =IFERROR(E5/D5-1,0) -> 0.079322333 | F6: =IFERROR(F5/E5-1,0) -> 0.10416156 | G6: =IFERROR(G5/F5-1,0) -> 0.1462879 | H6: =IFERROR(H5/G5-1,0) -> 0.13193734 | I6: =I5/H5-1 -> 0.27541082 | J6: =J5/I5-1 -> -0.17185984 | K6: =K5/J5-1 -> 0.14617881
B8: COGS | C8: =IFERROR(SUM('Data Sheet'!C18,'Data Sheet'!C20,'Data Sheet'!C21,'Data Sheet'!C22)-1*'Data Sheet'!C19,0) -> 6241.4 | D8: =IFERROR(SUM('Data Sheet'!D18,'Data Sheet'!D20,'Data Sheet'!D21,'Data Sheet'!D22)-1*'Data Sheet'!D19,0) -> 7003.97 | E8: =IFERROR(SUM('Data Sheet'!E18,'Data Sheet'!E20,'Data Sheet'!E21,'Data Sheet'!E22)-1*'Data Sheet'!E19,0) -> 7687.4 | F8: =IFERROR(SUM('Data Sheet'!F18,'Data Sheet'!F20,'Data Sheet'!F21,'Data Sheet'!F22)-1*'Data Sheet'!F19,0) -> 8521.15 | G8: =IFERROR(SUM('Data Sheet'!G18,'Data Sheet'!G20,'Data Sheet'!G21,'Data Sheet'!G22)-1*'Data Sheet'!G19,0) -> 10221.7 | H8: =IFERROR(SUM('Data Sheet'!H18,'Data Sheet'!H20,'Data Sheet'!H21,'Data Sheet'!H22)-1*'Data Sheet'!H19,0) -> 10281.89 | I8: =IFERROR(SUM('Data Sheet'!I18,'Data Sheet'!I20,'Data Sheet'!I21,'Data Sheet'!I22)-1*'Data Sheet'!I19,0) -> 14101.72 | J8: =IFERROR(SUM('Data Sheet'!J18,'Data Sheet'!J20,'Data Sheet'!J21,'Data Sheet'!J22)-1*'Data Sheet'!J19,0) -> 11692.86 | K8: =IFERROR(SUM('Data Sheet'!K18,'Data Sheet'!K20,'Data Sheet'!K21,'Data Sheet'!K22)-1*'Data Sheet'!K19,0) -> 13627.64
B9: Gross Margins | C9: =C8/C5 -> 0.55271438 | D9: =D8/D5 -> 0.5662565 | E9: =E8/E5 -> 0.57583391 | F9: =F8/F5 -> 0.57807388 | G9: =G8/G5 -> 0.60494314 | H9: =H8/H5 -> 0.53757862 | I9: =I8/I5 -> 0.5780841 | J9: =J8/J5 -> 0.57880976 | K9: =K8/K5 -> 0.58855001
B11: Gross Profit | C11: =C5-C8 -> 5050.87 | D11: =D5-D8 -> 5364.93 | E11: =E5-E8 -> 5662.63 | F11: =F5-F8 -> 6219.44 | G11: =G5-G8 -> 6675.26 | H11: =H5-H8 -> 8844.41 | I11: =I5-I8 -> 10292.17 | J11: =J5-J8 -> 8508.7 | K11: =K5-K8 -> 9526.96
B13: Selling & General Expenses | C13: =IFERROR(SUM('Data Sheet'!C23:C24),0) -> 2433.22 | D13: =IFERROR(SUM('Data Sheet'!D23:D24),0) -> 2439.05 | E13: =IFERROR(SUM('Data Sheet'!E23:E24),0) -> 2461.13 | F13: =IFERROR(SUM('Data Sheet'!F23:F24),0) -> 2657.04 | G13: =IFERROR(SUM('Data Sheet'!G23:G24),0) -> 2968.97 | H13: =IFERROR(SUM('Data Sheet'!H23:H24),0) -> 4373.42 | I13: =IFERROR(SUM('Data Sheet'!I23:I24),0) -> 4449.05 | J13: =IFERROR(SUM('Data Sheet'!J23:J24),0) -> 3737.37 | K13: =IFERROR(SUM('Data Sheet'!K23:K24),0) -> 4220
B14: S&G Exp % Sales | C14: =C13/C5 -> 0.2154766 | D14: =D13/D5 -> 0.19719215 | E14: =E13/E5 -> 0.18435389 | F14: =F13/F5 -> 0.1802533 | G14: =G13/G5 -> 0.17571031 | H14: =H13/H5 -> 0.22866001 | I14: =I13/I5 -> 0.18238379 | J14: =J13/J5 -> 0.18500403 | K14: =K13/K5 -> 0.1822532
B16: EBITDA | C16: =C11-C13 -> 2617.65 | D16: =D11-D13 -> 2925.88 | E16: =E11-E13 -> 3201.5 | F16: =F11-F13 -> 3562.4 | G16: =G11-G13 -> 3706.29 | H16: =H11-H13 -> 4470.99 | I16: =I11-I13 -> 5843.12 | J16: =J11-J13 -> 4771.33 | K16: =K11-K13 -> 5306.96
B17: EBITDA % Sales | C17: =C16/C5 -> 0.23180902 | D17: =D16/D5 -> 0.23655135 | E17: =E16/E5 -> 0.2398122 | F17: =F16/F5 -> 0.24167282 | G17: =G16/G5 -> 0.21934656 | H17: =H16/H5 -> 0.23376137 | I17: =I16/I5 -> 0.23953211 | J17: =J16/J5 -> 0.23618622 | K17: =K16/K5 -> 0.22919679
B19: Depreciation | C19: =IFERROR('Data Sheet'!C26,0) -> 335.67 | D19: =IFERROR('Data Sheet'!D26,0) -> 370.15 | E19: =IFERROR('Data Sheet'!E26,0) -> 370.38 | F19: =IFERROR('Data Sheet'!F26,0) -> 391.02 | G19: =IFERROR('Data Sheet'!G26,0) -> 403.01 | H19: =IFERROR('Data Sheet'!H26,0) -> 428.91 | I19: =IFERROR('Data Sheet'!I26,0) -> 567.75 | J19: =IFERROR('Data Sheet'!J26,0) -> 539.92 | K19: =IFERROR('Data Sheet'!K26,0) -> 699.23
B20: Depreciation % Sales | C20: =C19/C5 -> 0.029725644 | D20: =D19/D5 -> 0.029925862 | E20: =E19/E5 -> 0.027743758 | F20: =F19/F5 -> 0.026526754 | G20: =G19/G5 -> 0.023851036 | H20: =H19/H5 -> 0.022425142 | I20: =I19/I5 -> 0.023274271 | J20: =J19/J5 -> 0.026726649 | K20: =K19/K5 -> 0.030198319
B22: EBIT | C22: =C16-C19 -> 2281.98 | D22: =D16-D19 -> 2555.73 | E22: =E16-E19 -> 2831.12 | F22: =F16-F19 -> 3171.38 | G22: =G16-G19 -> 3303.28 | H22: =H16-H19 -> 4042.08 | I22: =I16-I19 -> 5275.37 | J22: =J16-J19 -> 4231.41 | K22: =K16-K19 -> 4607.73
B23: EBIT % Sales | C23: =C22/C5 -> 0.20208337 | D23: =D22/D5 -> 0.20662549 | E23: =E22/E5 -> 0.21206844 | F23: =F22/F5 -> 0.21514607 | G23: =G22/G5 -> 0.19549552 | H23: =H22/H5 -> 0.21133622 | I23: =I22/I5 -> 0.21625784 | J23: =J22/J5 -> 0.20945957 | K23: =K22/K5 -> 0.19899847
B25: Interest | C25: =IFERROR('Data Sheet'!C27,0) -> 111.95 | D25: =IFERROR('Data Sheet'!D27,0) -> 129.12 | E25: =IFERROR('Data Sheet'!E27,0) -> 164.18 | F25: =IFERROR('Data Sheet'!F27,0) -> 201.68 | G25: =IFERROR('Data Sheet'!G27,0) -> 154.57 | H25: =IFERROR('Data Sheet'!H27,0) -> 119.29 | I25: =IFERROR('Data Sheet'!I27,0) -> 145.49 | J25: =IFERROR('Data Sheet'!J27,0) -> 136 | K25: =IFERROR('Data Sheet'!K27,0) -> 158.31
B26: Interest % Sales | C26: =C25/C5 -> 0.0099138614 | D26: =D25/D5 -> 0.010439085 | E26: =E25/E5 -> 0.0122981 | F26: =F25/F5 -> 0.013681949 | G26: =G25/G5 -> 0.0091477994 | H26: =H25/H5 -> 0.0062369617 | I26: =I25/I5 -> 0.0059641984 | J26: =J25/J5 -> 0.0067321534 | K26: =K25/K5 -> 0.0068370864
B28: EBT | C28: =C16-C25-C19 -> 2170.03 | D28: =D16-D25-D19 -> 2426.61 | E28: =E16-E25-E19 -> 2666.94 | F28: =F16-F25-F19 -> 2969.7 | G28: =G16-G25-G19 -> 3148.71 | H28: =H16-H25-H19 -> 3922.79 | I28: =I16-I25-I19 -> 5129.88 | J28: =J16-J25-J19 -> 4095.41 | K28: =K16-K25-K19 -> 4449.42
B29: EBT % Sales | C29: =C28/C5 -> 0.19216951 | D29: =D28/D5 -> 0.1961864 | E29: =E28/E5 -> 0.19977034 | F29: =F28/F5 -> 0.20146412 | G29: =G28/G5 -> 0.18634772 | H29: =H28/H5 -> 0.20509926 | I29: =I28/I5 -> 0.21029364 | J29: =J28/J5 -> 0.20272741 | K29: =K28/K5 -> 0.19216138
B31: Tax | C31: =IFERROR('Data Sheet'!C29,0) -> 822.02 | D31: =IFERROR('Data Sheet'!D29,0) -> 705.05 | E31: =IFERROR('Data Sheet'!E29,0) -> 730.36 | F31: =IFERROR('Data Sheet'!F29,0) -> 738.91 | G31: =IFERROR('Data Sheet'!G29,0) -> 865.45 | H31: =IFERROR('Data Sheet'!H29,0) -> 1039.62 | I31: =IFERROR('Data Sheet'!I29,0) -> 1356.03 | J31: =IFERROR('Data Sheet'!J29,0) -> 1132.97 | K31: =IFERROR('Data Sheet'!K29,0) -> 1065.05
B32: Effective Tax Rate | C32: =C31/C28 -> 0.37880582 | D32: =D31/D28 -> 0.29054937 | E32: =E31/E28 -> 0.27385693 | F32: =F31/F28 -> 0.24881638 | G32: =G31/G28 -> 0.27485859 | H32: =H31/H28 -> 0.26502056 | I32: =I31/I28 -> 0.26433952 | J32: =J31/J28 -> 0.27664385 | K32: =K31/K28 -> 0.23936828
B34: Net Profit | C34: =C28-C31 -> 1348.01 | D34: =D28-D31 -> 1721.56 | E34: =E28-E31 -> 1936.58 | F34: =F28-F31 -> 2230.79 | G34: =G28-G31 -> 2283.26 | H34: =H28-H31 -> 2883.17 | I34: =I28-I31 -> 3773.85 | J34: =J28-J31 -> 2962.44 | K34: =K28-K31 -> 3384.37
B35: Net Margins | C35: =C34/C5 -> 0.11937458 | D35: =D34/D5 -> 0.13918457 | E35: =E34/E5 -> 0.14506185 | F35: =F34/F5 -> 0.15133655 | G35: =G34/G5 -> 0.13512845 | H35: =H34/H5 -> 0.15074374 | I35: =I34/I5 -> 0.15470472 | J35: =J34/J5 -> 0.14664412 | K35: =K34/K5 -> 0.14616405
B37: No. of Equity Shares | C37: =IFERROR('Data Sheet'!C93,0) -> 192.8 | D37: =IFERROR('Data Sheet'!D93,0) -> 192.8 | E37: =IFERROR('Data Sheet'!E93,0) -> 192.8 | F37: =IFERROR('Data Sheet'!F93,0) -> 192.8 | G37: =IFERROR('Data Sheet'!G93,0) -> 192.8 | H37: =IFERROR('Data Sheet'!H93,0) -> 192.8 | I37: =IFERROR('Data Sheet'!I93,0) -> 192.83 | J37: =IFERROR('Data Sheet'!J93,0) -> 192.83 | K37: =IFERROR('Data Sheet'!K93,0) -> 192.83
B39: EPS | C39: =IFERROR(C34/C37,0) -> 6.9917531 | D39: =IFERROR(D34/D37,0) -> 8.9292531 | E39: =IFERROR(E34/E37,0) -> 10.044502 | F39: =IFERROR(F34/F37,0) -> 11.570488 | G39: =IFERROR(G34/G37,0) -> 11.842635 | H39: =IFERROR(H34/H37,0) -> 14.954201 | I39: =IFERROR(I34/I37,0) -> 19.570866 | J39: =IFERROR(J34/J37,0) -> 15.362962 | K39: =IFERROR(K34/K37,0) -> 17.551055
B40: EPS Growth | C40: - | D40: =IFERROR(D42/C42,0) -> 2.9739094 | E40: =IFERROR(E42/D42,0) -> 0.58479603 | F40: =IFERROR(F42/E42,0) -> 1 | G40: =IFERROR(G42/F42,0) -> 1.1 | H40: =IFERROR(H42/G42,0) -> 0.79091003 | I40: =I42/H42 -> 1.8502822 | J40: =J42/I42 -> 0.8385104 | K40: =K42/J42 -> 0.88884279
B42: Dividend per Share | C42: =IFERROR('Data Sheet'!C31/'Historical FS'!C37,0) -> 5.7511929 | D42: =IFERROR('Data Sheet'!D31/'Historical FS'!D37,0) -> 17.103527 | E42: =IFERROR('Data Sheet'!E31/'Historical FS'!E37,0) -> 10.002075 | F42: =IFERROR('Data Sheet'!F31/'Historical FS'!F37,0) -> 10.002075 | G42: =IFERROR('Data Sheet'!G31/'Historical FS'!G37,0) -> 11.002282 | H42: =IFERROR('Data Sheet'!H31/'Historical FS'!H37,0) -> 8.7018154 | I42: =IFERROR('Data Sheet'!I31/'Historical FS'!I37,0) -> 16.100814 | J42: =IFERROR('Data Sheet'!J31/'Historical FS'!J37,0) -> 13.5007 | K42: =IFERROR('Data Sheet'!K31/'Historical FS'!K37,0) -> 12
B43: Dividend Payout Ratio | C43: =IFERROR(C42/C39,0) -> 0.82256808 | D43: =IFERROR(D42/D39,0) -> 1.9154488 | E43: =IFERROR(E42/E39,0) -> 0.99577606 | F43: =IFERROR(F42/F39,0) -> 0.86444712 | G43: =IFERROR(G42/G39,0) -> 0.92904006 | H43: =IFERROR(H42/H39,0) -> 0.5818977 | I43: =IFERROR(I42/I39,0) -> 0.82269301 | J43: =IFERROR(J42/J39,0) -> 0.87878236 | K43: =IFERROR(K42/K39,0) -> 0.68371957
B45: Retained Earnings | C45: =IFERROR(IF(C39>C42,1-C43,0),0) -> 0.17743192 | D45: =IFERROR(IF(D39>D42,1-D43,0),0) -> 0 | E45: =IFERROR(IF(E39>E42,1-E43,0),0) -> 0.0042239412 | F45: =IFERROR(IF(F39>F42,1-F43,0),0) -> 0.13555288 | G45: =IFERROR(IF(G39>G42,1-G43,0),0) -> 0.070959943 | H45: =IFERROR(IF(H39>H42,1-H43,0),0) -> 0.4181023 | I45: =IFERROR(IF(I39>I42,1-I43,0),0) -> 0.17730699 | J45: =IFERROR(IF(J39>J42,1-J43,0),0) -> 0.12121764 | K45: =IFERROR(IF(K39>K42,1-K43,0),0) -> 0.31628043
A47: # | B47: Balance Sheet
B48: Equity Share Capital | C48: =IFERROR('Data Sheet'!C57,0) -> 96.42 | D48: =IFERROR('Data Sheet'!D57,0) -> 96.42 | E48: =IFERROR('Data Sheet'!E57,0) -> 96.42 | F48: =IFERROR('Data Sheet'!F57,0) -> 96.42 | G48: =IFERROR('Data Sheet'!G57,0) -> 96.42 | H48: =IFERROR('Data Sheet'!H57,0) -> 96.42 | I48: =IFERROR('Data Sheet'!I57,0) -> 96.42 | J48: =IFERROR('Data Sheet'!J57,0) -> 96.42 | K48: =IFERROR('Data Sheet'!K57,0) -> 192.83
B49: Reserves | C49: =IFERROR('Data Sheet'!C58,0) -> 3577.32 | D49: =IFERROR('Data Sheet'!D58,0) -> 1822.45 | E49: =IFERROR('Data Sheet'!E58,0) -> 1922.92 | F49: =IFERROR('Data Sheet'!F58,0) -> 1849.96 | G49: =IFERROR('Data Sheet'!G58,0) -> 2362.75 | H49: =IFERROR('Data Sheet'!H58,0) -> 2362.75 | I49: =IFERROR('Data Sheet'!I58,0) -> 3244.47 | J49: =IFERROR('Data Sheet'!J58,0) -> 4020.73 | K49: =IFERROR('Data Sheet'!K58,0) -> 5116.41
B50: Borrowings | C50: =IFERROR('Data Sheet'!C59,0) -> 35.14 | D50: =IFERROR('Data Sheet'!D59,0) -> 188.94 | E50: =IFERROR('Data Sheet'!E59,0) -> 147.49 | F50: =IFERROR('Data Sheet'!F59,0) -> 266.46 | G50: =IFERROR('Data Sheet'!G59,0) -> 270.52 | H50: =IFERROR('Data Sheet'!H59,0) -> 270.52 | I50: =IFERROR('Data Sheet'!I59,0) -> 344.53 | J50: =IFERROR('Data Sheet'!J59,0) -> 1166.85 | K50: =IFERROR('Data Sheet'!K59,0) -> 444.16
B51: Other Liabilities | C51: =IFERROR('Data Sheet'!C60,0) -> 4379.2 | D51: =IFERROR('Data Sheet'!D60,0) -> 5065.13 | E51: =IFERROR('Data Sheet'!E60,0) -> 5732.9 | F51: =IFERROR('Data Sheet'!F60,0) -> 6021.29 | G51: =IFERROR('Data Sheet'!G60,0) -> 6249.05 | H51: =IFERROR('Data Sheet'!H60,0) -> 6249.05 | I51: =IFERROR('Data Sheet'!I60,0) -> 6837.64 | J51: =IFERROR('Data Sheet'!J60,0) -> 7039.89 | K51: =IFERROR('Data Sheet'!K60,0) -> 7603.77
B52: Total Liabilities | C52: =IFERROR('Data Sheet'!C61,0) -> 8088.08 | D52: =IFERROR('Data Sheet'!D61,0) -> 7172.94 | E52: =IFERROR('Data Sheet'!E61,0) -> 7899.73 | F52: =IFERROR('Data Sheet'!F61,0) -> 8234.13 | G52: =IFERROR('Data Sheet'!G61,0) -> 8978.74 | H52: =IFERROR('Data Sheet'!H61,0) -> 8978.74 | I52: =IFERROR('Data Sheet'!I61,0) -> 10523.06 | J52: =IFERROR('Data Sheet'!J61,0) -> 12323.89 | K52: =IFERROR('Data Sheet'!K61,0) -> 13357.17
B54: Fixed Assets Net Block | C54: =IFERROR('Data Sheet'!C62,0) -> 2400.62 | D54: =IFERROR('Data Sheet'!D62,0) -> 2341.45 | E54: =IFERROR('Data Sheet'!E62,0) -> 2179.41 | F54: =IFERROR('Data Sheet'!F62,0) -> 2994.67 | G54: =IFERROR('Data Sheet'!G62,0) -> 3043.7 | H54: =IFERROR('Data Sheet'!H62,0) -> 3043.7 | I54: =IFERROR('Data Sheet'!I62,0) -> 3460.25 | J54: =IFERROR('Data Sheet'!J62,0) -> 5473.61 | K54: =IFERROR('Data Sheet'!K62,0) -> 6290.42
B55: Capital Work in Progress | C55: =IFERROR('Data Sheet'!C63,0) -> 105.2 | D55: =IFERROR('Data Sheet'!D63,0) -> 143.3 | E55: =IFERROR('Data Sheet'!E63,0) -> 638.58 | F55: =IFERROR('Data Sheet'!F63,0) -> 246.23 | G55: =IFERROR('Data Sheet'!G63,0) -> 358.36 | H55: =IFERROR('Data Sheet'!H63,0) -> 358.36 | I55: =IFERROR('Data Sheet'!I63,0) -> 1741.71 | J55: =IFERROR('Data Sheet'!J63,0) -> 1172.56 | K55: =IFERROR('Data Sheet'!K63,0) -> 506.98
B56: Investments | C56: =IFERROR('Data Sheet'!C64,0) -> 2658.49 | D56: =IFERROR('Data Sheet'!D64,0) -> 1751.05 | E56: =IFERROR('Data Sheet'!E64,0) -> 1463.77 | F56: =IFERROR('Data Sheet'!F64,0) -> 773.98 | G56: =IFERROR('Data Sheet'!G64,0) -> 777.54 | H56: =IFERROR('Data Sheet'!H64,0) -> 777.54 | I56: =IFERROR('Data Sheet'!I64,0) -> 463.87 | J56: =IFERROR('Data Sheet'!J64,0) -> 705.6 | K56: =IFERROR('Data Sheet'!K64,0) -> 705.6
B57: Other Assets | C57: =IFERROR('Data Sheet'!C65-SUM('Data Sheet'!C67:C69),0) -> 223.57 | D57: =IFERROR('Data Sheet'!D65-SUM('Data Sheet'!D67:D69),0) -> 221.69 | E57: =IFERROR('Data Sheet'!E65-SUM('Data Sheet'!E67:E69),0) -> 266.69 | F57: =IFERROR('Data Sheet'!F65-SUM('Data Sheet'!F67:F69),0) -> 1725.22 | G57: =IFERROR('Data Sheet'!G65-SUM('Data Sheet'!G67:G69),0) -> 1732.93 | H57: =IFERROR('Data Sheet'!H65-SUM('Data Sheet'!H67:H69),0) -> 1732.93 | I57: =IFERROR('Data Sheet'!I65-SUM('Data Sheet'!I67:I69),0) -> 1688.56 | J57: =IFERROR('Data Sheet'!J65-SUM('Data Sheet'!J67:J69),0) -> 1663.18 | K57: =IFERROR('Data Sheet'!K65-SUM('Data Sheet'!K67:K69),0) -> 1614.61
B58: Total Non Current Assets | C58: =SUM(C54:C57) -> 5387.88 | D58: =SUM(D54:D57) -> 4457.49 | E58: =SUM(E54:E57) -> 4548.45 | F58: =SUM(F54:F57) -> 5740.1 | G58: =SUM(G54:G57) -> 5912.53 | H58: =SUM(H54:H57) -> 5912.53 | I58: =SUM(I54:I57) -> 7354.39 | J58: =SUM(J54:J57) -> 9014.95 | K58: =SUM(K54:K57) -> 9117.61
B60: Receivables | C60: =IFERROR('Data Sheet'!C67,0) -> 124.59 | D60: =IFERROR('Data Sheet'!D67,0) -> 124.33 | E60: =IFERROR('Data Sheet'!E67,0) -> 164.93 | F60: =IFERROR('Data Sheet'!F67,0) -> 165.97 | G60: =IFERROR('Data Sheet'!G67,0) -> 191.89 | H60: =IFERROR('Data Sheet'!H67,0) -> 191.89 | I60: =IFERROR('Data Sheet'!I67,0) -> 300.46 | J60: =IFERROR('Data Sheet'!J67,0) -> 363.15 | K60: =IFERROR('Data Sheet'!K67,0) -> 329.47
B61: Inventory | C61: =IFERROR('Data Sheet'!C68,0) -> 965.55 | D61: =IFERROR('Data Sheet'!D68,0) -> 1283.07 | E61: =IFERROR('Data Sheet'!E68,0) -> 1416.48 | F61: =IFERROR('Data Sheet'!F68,0) -> 1592.65 | G61: =IFERROR('Data Sheet'!G68,0) -> 1928.77 | H61: =IFERROR('Data Sheet'!H68,0) -> 1928.77 | I61: =IFERROR('Data Sheet'!I68,0) -> 2089.36 | J61: =IFERROR('Data Sheet'!J68,0) -> 2850.14 | K61: =IFERROR('Data Sheet'!K68,0) -> 2569.22
B62: Cash & Bank | C62: =IFERROR('Data Sheet'!C69,0) -> 1610.06 | D62: =IFERROR('Data Sheet'!D69,0) -> 1308.05 | E62: =IFERROR('Data Sheet'!E69,0) -> 1769.87 | F62: =IFERROR('Data Sheet'!F69,0) -> 735.41 | G62: =IFERROR('Data Sheet'!G69,0) -> 945.55 | H62: =IFERROR('Data Sheet'!H69,0) -> 945.55 | I62: =IFERROR('Data Sheet'!I69,0) -> 778.85 | J62: =IFERROR('Data Sheet'!J69,0) -> 95.65 | K62: =IFERROR('Data Sheet'!K69,0) -> 1340.87
B63: Total Current Assets | C63: =IFERROR(SUM(C60:C62),0) -> 2700.2 | D63: =IFERROR(SUM(D60:D62),0) -> 2715.45 | E63: =IFERROR(SUM(E60:E62),0) -> 3351.28 | F63: =IFERROR(SUM(F60:F62),0) -> 2494.03 | G63: =IFERROR(SUM(G60:G62),0) -> 3066.21 | H63: =IFERROR(SUM(H60:H62),0) -> 3066.21 | I63: =IFERROR(SUM(I60:I62),0) -> 3168.67 | J63: =IFERROR(SUM(J60:J62),0) -> 3308.94 | K63: =IFERROR(SUM(K60:K62),0) -> 4239.56
B65: Total Assets | C65: =IFERROR(C58+C63,0) -> 8088.08 | D65: =IFERROR(D58+D63,0) -> 7172.94 | E65: =IFERROR(E58+E63,0) -> 7899.73 | F65: =IFERROR(F58+F63,0) -> 8234.13 | G65: =IFERROR(G58+G63,0) -> 8978.74 | H65: =IFERROR(H58+H63,0) -> 8978.74 | I65: =IFERROR(I58+I63,0) -> 10523.06 | J65: =IFERROR(J58+J63,0) -> 12323.89 | K65: =IFERROR(K58+K63,0) -> 13357.17
B67: Check | C67: =C65=C52 -> TRUE | D67: =D65=D52 -> TRUE | E67: =E65=E52 -> TRUE | F67: =F65=F52 -> TRUE | G67: =G65=G52 -> TRUE | H67: =H65=H52 -> TRUE | I67: =I65=I52 -> TRUE | J67: =J65=J52 -> TRUE | K67: =K65=K52 -> TRUE
A69: # | B69: Cash Flow Statement
B70: Operating Activity -
B71: Profit from operations | C71: =IFERROR('Cash Flow Data'!C3,0) -> 2521 | D71: =IFERROR('Cash Flow Data'!D3,0) -> 2805 | E71: =IFERROR('Cash Flow Data'!E3,0) -> 3061 | F71: =IFERROR('Cash Flow Data'!F3,0) -> 3136 | G71: =IFERROR('Cash Flow Data'!G3,0) -> 3609 | H71: =IFERROR('Cash Flow Data'!H3,0) -> 4388 | I71: =IFERROR('Cash Flow Data'!I3,0) -> 5722 | J71: =IFERROR('Cash Flow Data'!J3,0) -> 4672 | K71: =IFERROR('Cash Flow Data'!K3,0) -> 5326
B72: Receivables | C72: =IFERROR('Cash Flow Data'!C4,0) -> -36 | D72: =IFERROR('Cash Flow Data'!D4,0) -> 0 | E72: =IFERROR('Cash Flow Data'!E4,0) -> -42 | F72: =IFERROR('Cash Flow Data'!F4,0) -> -2 | G72: =IFERROR('Cash Flow Data'!G4,0) -> -28 | H72: =IFERROR('Cash Flow Data'!H4,0) -> -11 | I72: =IFERROR('Cash Flow Data'!I4,0) -> -109 | J72: =IFERROR('Cash Flow Data'!J4,0) -> -70 | K72: =IFERROR('Cash Flow Data'!K4,0) -> 34
B73: Inventory | C73: =IFERROR('Cash Flow Data'!C5,0) -> -63 | D73: =IFERROR('Cash Flow Data'!D5,0) -> -318 | E73: =IFERROR('Cash Flow Data'!E5,0) -> -133 | F73: =IFERROR('Cash Flow Data'!F5,0) -> -169 | G73: =IFERROR('Cash Flow Data'!G5,0) -> -336 | H73: =IFERROR('Cash Flow Data'!H5,0) -> 56 | I73: =IFERROR('Cash Flow Data'!I5,0) -> -161 | J73: =IFERROR('Cash Flow Data'!J5,0) -> -767 | K73: =IFERROR('Cash Flow Data'!K5,0) -> 281
B74: Payables | C74: =IFERROR('Cash Flow Data'!C6,0) -> 257 | D74: =IFERROR('Cash Flow Data'!D6,0) -> 253 | E74: =IFERROR('Cash Flow Data'!E6,0) -> 23 | F74: =IFERROR('Cash Flow Data'!F6,0) -> 217 | G74: =IFERROR('Cash Flow Data'!G6,0) -> 178 | H74: =IFERROR('Cash Flow Data'!H6,0) -> 68 | I74: =IFERROR('Cash Flow Data'!I6,0) -> 310 | J74: =IFERROR('Cash Flow Data'!J6,0) -> 134 | K74: =IFERROR('Cash Flow Data'!K6,0) -> 588
B75: Loans Advances | C75: =IFERROR('Cash Flow Data'!C7,0) -> 0 | D75: =IFERROR('Cash Flow Data'!D7,0) -> 0 | E75: =IFERROR('Cash Flow Data'!E7,0) -> 0 | F75: =IFERROR('Cash Flow Data'!F7,0) -> -40 | G75: =IFERROR('Cash Flow Data'!G7,0) -> -30 | H75: =IFERROR('Cash Flow Data'!H7,0) -> -30 | I75: =IFERROR('Cash Flow Data'!I7,0) -> -21 | J75: =IFERROR('Cash Flow Data'!J7,0) -> -199 | K75: =IFERROR('Cash Flow Data'!K7,0) -> -73
B76: Other WC items | C76: =IFERROR('Cash Flow Data'!C9,0) -> 255 | D76: =IFERROR('Cash Flow Data'!D9,0) -> 227 | E76: =IFERROR('Cash Flow Data'!E9,0) -> 249 | F76: =IFERROR('Cash Flow Data'!F9,0) -> -179 | G76: =IFERROR('Cash Flow Data'!G9,0) -> 185 | H76: =IFERROR('Cash Flow Data'!H9,0) -> -19 | I76: =IFERROR('Cash Flow Data'!I9,0) -> -268 | J76: =IFERROR('Cash Flow Data'!J9,0) -> 155 | K76: =IFERROR('Cash Flow Data'!K9,0) -> -37
B77: Working capital changes | C77: =IFERROR('Cash Flow Data'!C10,0) -> 413 | D77: =IFERROR('Cash Flow Data'!D10,0) -> 163 | E77: =IFERROR('Cash Flow Data'!E10,0) -> 97 | F77: =IFERROR('Cash Flow Data'!F10,0) -> -172 | G77: =IFERROR('Cash Flow Data'!G10,0) -> -30 | H77: =IFERROR('Cash Flow Data'!H10,0) -> 63 | I77: =IFERROR('Cash Flow Data'!I10,0) -> -249 | J77: =IFERROR('Cash Flow Data'!J10,0) -> -747 | K77: =IFERROR('Cash Flow Data'!K10,0) -> 793
B78: Direct taxes | C78: =IFERROR('Cash Flow Data'!C11,0) -> -881 | D78: =IFERROR('Cash Flow Data'!D11,0) -> -673 | E78: =IFERROR('Cash Flow Data'!E11,0) -> -703 | F78: =IFERROR('Cash Flow Data'!F11,0) -> -729 | G78: =IFERROR('Cash Flow Data'!G11,0) -> -841 | H78: =IFERROR('Cash Flow Data'!H11,0) -> -1059 | I78: =IFERROR('Cash Flow Data'!I11,0) -> -1299 | J78: =IFERROR('Cash Flow Data'!J11,0) -> -990 | K78: =IFERROR('Cash Flow Data'!K11,0) -> -1071
B79: Cash from Operating Activity - | C79: =IFERROR('Cash Flow Data'!C2,0) -> 2052 | D79: =IFERROR('Cash Flow Data'!D2,0) -> 2295 | E79: =IFERROR('Cash Flow Data'!E2,0) -> 2454 | F79: =IFERROR('Cash Flow Data'!F2,0) -> 2236 | G79: =IFERROR('Cash Flow Data'!G2,0) -> 2737 | H79: =IFERROR('Cash Flow Data'!H2,0) -> 3392 | I79: =IFERROR('Cash Flow Data'!I2,0) -> 4175 | J79: =IFERROR('Cash Flow Data'!J2,0) -> 2935 | K79: =IFERROR('Cash Flow Data'!K2,0) -> 5048
B81: Investing Activity -
B82: Fixed assets purchased | C82: =IFERROR('Cash Flow Data'!C13,0) -> -166 | D82: =IFERROR('Cash Flow Data'!D13,0) -> -155 | E82: =IFERROR('Cash Flow Data'!E13,0) -> -478 | F82: =IFERROR('Cash Flow Data'!F13,0) -> -735 | G82: =IFERROR('Cash Flow Data'!G13,0) -> -550 | H82: =IFERROR('Cash Flow Data'!H13,0) -> -1371 | I82: =IFERROR('Cash Flow Data'!I13,0) -> -1883 | J82: =IFERROR('Cash Flow Data'!J13,0) -> -2009 | K82: =IFERROR('Cash Flow Data'!K13,0) -> -830
B83: Fixed assets sold | C83: =IFERROR('Cash Flow Data'!C14,0) -> 3 | D83: =IFERROR('Cash Flow Data'!D14,0) -> 2 | E83: =IFERROR('Cash Flow Data'!E14,0) -> 4 | F83: =IFERROR('Cash Flow Data'!F14,0) -> 4 | G83: =IFERROR('Cash Flow Data'!G14,0) -> 9 | H83: =IFERROR('Cash Flow Data'!H14,0) -> 7 | I83: =IFERROR('Cash Flow Data'!I14,0) -> 4 | J83: =IFERROR('Cash Flow Data'!J14,0) -> 4 | K83: =IFERROR('Cash Flow Data'!K14,0) -> 3
B84: Investments purchased | C84: =IFERROR('Cash Flow Data'!C15,0) -> -160 | D84: =IFERROR('Cash Flow Data'!D15,0) -> -16 | E84: =IFERROR('Cash Flow Data'!E15,0) -> 0 | F84: =IFERROR('Cash Flow Data'!F15,0) -> 0 | G84: =IFERROR('Cash Flow Data'!G15,0) -> 0 | H84: =IFERROR('Cash Flow Data'!H15,0) -> 0 | I84: =IFERROR('Cash Flow Data'!I15,0) -> 0 | J84: =IFERROR('Cash Flow Data'!J15,0) -> 0 | K84: =IFERROR('Cash Flow Data'!K15,0) -> 0
B85: Investments sold | C85: =IFERROR('Cash Flow Data'!C16,0) -> 0 | D85: =IFERROR('Cash Flow Data'!D16,0) -> 0 | E85: =IFERROR('Cash Flow Data'!E16,0) -> 0 | F85: =IFERROR('Cash Flow Data'!F16,0) -> 0 | G85: =IFERROR('Cash Flow Data'!G16,0) -> 25 | H85: =IFERROR('Cash Flow Data'!H16,0) -> 312 | I85: =IFERROR('Cash Flow Data'!I16,0) -> 284 | J85: =IFERROR('Cash Flow Data'!J16,0) -> 424 | K85: =IFERROR('Cash Flow Data'!K16,0) -> 0
B86: Interest received | C86: =IFERROR('Cash Flow Data'!C17,0) -> 237 | D86: =IFERROR('Cash Flow Data'!D17,0) -> 238 | E86: =IFERROR('Cash Flow Data'!E17,0) -> 148 | F86: =IFERROR('Cash Flow Data'!F17,0) -> 125 | G86: =IFERROR('Cash Flow Data'!G17,0) -> 103 | H86: =IFERROR('Cash Flow Data'!H17,0) -> 0 | I86: =IFERROR('Cash Flow Data'!I17,0) -> 167 | J86: =IFERROR('Cash Flow Data'!J17,0) -> 76 | K86: =IFERROR('Cash Flow Data'!K17,0) -> 34
B87: Dividends received | C87: =IFERROR('Cash Flow Data'!C18,0) -> 19 | D87: =IFERROR('Cash Flow Data'!D18,0) -> 13 | E87: =IFERROR('Cash Flow Data'!E18,0) -> 2 | F87: =IFERROR('Cash Flow Data'!F18,0) -> 0 | G87: =IFERROR('Cash Flow Data'!G18,0) -> 0 | H87: =IFERROR('Cash Flow Data'!H18,0) -> 0 | I87: =IFERROR('Cash Flow Data'!I18,0) -> 0 | J87: =IFERROR('Cash Flow Data'!J18,0) -> 0 | K87: =IFERROR('Cash Flow Data'!K18,0) -> 0
B88: Acquisition of companies | C88: =IFERROR('Cash Flow Data'!C19,0) -> 0 | D88: =IFERROR('Cash Flow Data'!D19,0) -> 0 | E88: =IFERROR('Cash Flow Data'!E19,0) -> 0 | F88: =IFERROR('Cash Flow Data'!F19,0) -> 0 | G88: =IFERROR('Cash Flow Data'!G19,0) -> 0 | H88: =IFERROR('Cash Flow Data'!H19,0) -> 0 | I88: =IFERROR('Cash Flow Data'!I19,0) -> 0 | J88: =IFERROR('Cash Flow Data'!J19,0) -> -706 | K88: =IFERROR('Cash Flow Data'!K19,0) -> 0
B89: Inter corporate deposits | C89: 0 | D89: 0 | E89: 0 | F89: 0 | G89: 0 | H89: 0 | I89: 0 | J89: 0 | K89: 0
B90: Other investing items | C90: =IFERROR('Cash Flow Data'!C20,0) -> 15 | D90: =IFERROR('Cash Flow Data'!D20,0) -> 0 | E90: =IFERROR('Cash Flow Data'!E20,0) -> 3 | F90: =IFERROR('Cash Flow Data'!F20,0) -> -1314 | G90: =IFERROR('Cash Flow Data'!G20,0) -> 20 | H90: =IFERROR('Cash Flow Data'!H20,0) -> 126 | I90: =IFERROR('Cash Flow Data'!I20,0) -> 190 | J90: =IFERROR('Cash Flow Data'!J20,0) -> 400 | K90: =IFERROR('Cash Flow Data'!K20,0) -> 168
B91: Cash from Investing Activity - | C91: =IFERROR('Cash Flow Data'!C12,0) -> -52 | D91: =IFERROR('Cash Flow Data'!D12,0) -> 83 | E91: =IFERROR('Cash Flow Data'!E12,0) -> -321 | F91: =IFERROR('Cash Flow Data'!F12,0) -> -1920 | G91: =IFERROR('Cash Flow Data'!G12,0) -> -392 | H91: =IFERROR('Cash Flow Data'!H12,0) -> -927 | I91: =IFERROR('Cash Flow Data'!I12,0) -> -1237 | J91: =IFERROR('Cash Flow Data'!J12,0) -> -1811 | K91: =IFERROR('Cash Flow Data'!K12,0) -> -624
B93: Financing Activity -
B94: Proceeds from shares | C94: 0 | D94: 0 | E94: 0 | F94: 0 | G94: 0 | H94: 0 | I94: 0 | J94: 0 | K94: 0
B95: Proceeds from borrowings | C95: =IFERROR('Cash Flow Data'!C22,0) -> 0 | D95: =IFERROR('Cash Flow Data'!D22,0) -> 0 | E95: =IFERROR('Cash Flow Data'!E22,0) -> 0 | F95: =IFERROR('Cash Flow Data'!F22,0) -> 24 | G95: =IFERROR('Cash Flow Data'!G22,0) -> 0 | H95: =IFERROR('Cash Flow Data'!H22,0) -> 0 | I95: =IFERROR('Cash Flow Data'!I22,0) -> 0 | J95: =IFERROR('Cash Flow Data'!J22,0) -> 726 | K95: =IFERROR('Cash Flow Data'!K22,0) -> 0
B96: Repayment of borrowings | C96: =IFERROR('Cash Flow Data'!C23,0) -> 0 | D96: =IFERROR('Cash Flow Data'!D23,0) -> 0 | E96: =IFERROR('Cash Flow Data'!E23,0) -> 0 | F96: =IFERROR('Cash Flow Data'!F23,0) -> -24 | G96: =IFERROR('Cash Flow Data'!G23,0) -> 0 | H96: =IFERROR('Cash Flow Data'!H23,0) -> 0 | I96: =IFERROR('Cash Flow Data'!I23,0) -> 0 | J96: =IFERROR('Cash Flow Data'!J23,0) -> 0 | K96: =IFERROR('Cash Flow Data'!K23,0) -> -726
B97: Interest paid fin | C97: =IFERROR('Cash Flow Data'!C25,0) -> -4 | D97: =IFERROR('Cash Flow Data'!D25,0) -> -63 | E97: =IFERROR('Cash Flow Data'!E25,0) -> -69 | F97: =IFERROR('Cash Flow Data'!F25,0) -> -9 | G97: =IFERROR('Cash Flow Data'!G25,0) -> -18 | H97: =IFERROR('Cash Flow Data'!H25,0) -> -20 | I97: =IFERROR('Cash Flow Data'!I25,0) -> -26 | J97: =IFERROR('Cash Flow Data'!J25,0) -> -34 | K97: =IFERROR('Cash Flow Data'!K25,0) -> -50
B98: Dividends paid | C98: =IFERROR('Cash Flow Data'!C26,0) -> -1090 | D98: =IFERROR('Cash Flow Data'!D26,0) -> -2950 | E98: =IFERROR('Cash Flow Data'!E26,0) -> -1890 | F98: =IFERROR('Cash Flow Data'!F26,0) -> -1928 | G98: =IFERROR('Cash Flow Data'!G26,0) -> -2025 | H98: =IFERROR('Cash Flow Data'!H26,0) -> -2333 | I98: =IFERROR('Cash Flow Data'!I26,0) -> -3008 | J98: =IFERROR('Cash Flow Data'!J26,0) -> -2459 | K98: =IFERROR('Cash Flow Data'!K26,0) -> -2314
B99: Financial liabilities | C99: =IFERROR('Cash Flow Data'!C27,0) -> 0 | D99: =IFERROR('Cash Flow Data'!D27,0) -> 0 | E99: =IFERROR('Cash Flow Data'!E27,0) -> 0 | F99: =IFERROR('Cash Flow Data'!F27,0) -> -79 | G99: =IFERROR('Cash Flow Data'!G27,0) -> -73 | H99: =IFERROR('Cash Flow Data'!H27,0) -> -166 | I99: =IFERROR('Cash Flow Data'!I27,0) -> -100 | J99: =IFERROR('Cash Flow Data'!J27,0) -> -76 | K99: =IFERROR('Cash Flow Data'!K27,0) -> -86
B100: Other financing items | C100: =IFERROR('Cash Flow Data'!C28,0) -> -224 | D100: =IFERROR('Cash Flow Data'!D28,0) -> -588 | E100: =IFERROR('Cash Flow Data'!E28,0) -> 3 | F100: =IFERROR('Cash Flow Data'!F28,0) -> -3 | G100: =IFERROR('Cash Flow Data'!G28,0) -> -7 | H100: =IFERROR('Cash Flow Data'!H28,0) -> 83 | I100: =IFERROR('Cash Flow Data'!I28,0) -> -1 | J100: =IFERROR('Cash Flow Data'!J28,0) -> -4 | K100: =IFERROR('Cash Flow Data'!K28,0) -> -3
B101: Cash from Financing Activity - | C101: =IFERROR('Cash Flow Data'!C21,0) -> -1317 | D101: =IFERROR('Cash Flow Data'!D21,0) -> -3602 | E101: =IFERROR('Cash Flow Data'!E21,0) -> -1956 | F101: =IFERROR('Cash Flow Data'!F21,0) -> -2020 | G101: =IFERROR('Cash Flow Data'!G21,0) -> -2123 | H101: =IFERROR('Cash Flow Data'!H21,0) -> -2436 | I101: =IFERROR('Cash Flow Data'!I21,0) -> -3135 | J101: =IFERROR('Cash Flow Data'!J21,0) -> -1846 | K101: =IFERROR('Cash Flow Data'!K21,0) -> -3179
B103: Net Cash Flow | C103: =SUM(C79,C91,C101) -> 683 | D103: =SUM(D79,D91,D101) -> -1224 | E103: =SUM(E79,E91,E101) -> 177 | F103: =SUM(F79,F91,F101) -> -1704 | G103: =SUM(G79,G91,G101) -> 222 | H103: =SUM(H79,H91,H101) -> 29 | I103: =SUM(I79,I91,I101) -> -197 | J103: =SUM(J79,J91,J101) -> -722 | K103: =SUM(K79,K91,K101) -> 1245

Sheet Data Sheet
A1: COMPANY NAME | B1: NESTLE INDIA LTD | E1: =IF(B2<>B3, "A NEW VERSION OF THE WORKSHEET IS AVAILABLE", "")
A2: LATEST VERSION | B2: 2.1 | E2: PLEASE DO NOT MAKE ANY CHANGES TO THIS SHEET
A3: CURRENT VERSION | B3: 2.1
A5: META
A6: Number of shares | B6: =IF(B9>0, B9/B8, 0) -> 192.83143
A7: Face Value | B7: 1
A8: Current Price | B8: 1382.65
A9: Market Capitalization | B9: 266618.37
A15: PROFIT & LOSS
A16: Report Date | B16: 43100 | C16: 43465 | D16: 43830 | E16: 44196 | F16: 44561 | G16: 44926 | H16: 45291 | I16: 45382 | J16: 45747 | K16: 46112
A17: Sales | B17: 10009.6 | C17: 11292.27 | D17: 12368.9 | E17: 13350.03 | F17: 14740.59 | G17: 16896.96 | H17: 19126.3 | I17: 24393.89 | J17: 20201.56 | K17: 23154.6
A18: Raw Material Cost | B18: 3696.99 | C18: 3829.22 | D18: 4520.91 | E18: 4901.74 | F18: 5301.26 | G18: 6660.42 | H18: 8472.72 | I18: 9201.11 | J18: 7646.63 | K18: 9113.96
A19: Change in Inventory | B19: 79.56 | C19: 6.01 | D19: 144.19 | E19: 69.33 | F19: 67.59 | G19: 250.27 | H19: 40.01 | I19: 45.68 | J19: 139.66 | K19: 168.23
A20: Power and Fuel | B20: 288.44 | C20: 344.18 | D20: 340.53 | E20: 313.68 | F20: 408.06 | G20: 572.61 | I20: 674.83 | J20: 541.42 | K20: 587.21
A21: Other Mfr. Exp | B21: 897.84 | C21: 949.86 | D21: 1028.55 | E21: 1040.36 | F21: 1349.48 | G21: 1603.48 | I21: 1935.4 | J21: 1582.45 | K21: 1816.29
A22: Employee Cost | B22: 1017.45 | C22: 1124.15 | D22: 1258.17 | E22: 1500.95 | F22: 1529.94 | G22: 1635.46 | H22: 1849.18 | I22: 2336.06 | J22: 2062.02 | K22: 2278.41
A23: Selling and admin | B23: 1823.98 | C23: 2145.82 | D23: 2226.13 | E23: 2246.9 | F23: 2902.12 | G23: 3192.15 | I23: 4837.58 | J23: 4126.54 | K23: 4780.9
A24: Other Expenses | B24: 267.93 | C24: 287.4 | D24: 212.92 | E24: 214.23 | F24: -245.08 | G24: -223.18 | H24: 4373.42 | I24: -388.53 | J24: -389.17 | K24: -560.9
A25: Other Income | B25: 176.92 | C25: 258.92 | D25: 246.88 | E25: 145.85 | F25: -112.38 | G25: 107.26 | H25: 115.5 | I25: 158.99 | J25: 352.06 | K25: 160.23
A26: Depreciation | B26: 342.25 | C26: 335.67 | D26: 370.15 | E26: 370.38 | F26: 391.02 | G26: 403.01 | H26: 428.91 | I26: 567.75 | J26: 539.92 | K26: 699.23
A27: Interest | B27: 91.9 | C27: 111.95 | D27: 129.12 | E27: 164.18 | F27: 201.68 | G27: 154.57 | H27: 119.29 | I27: 145.49 | J27: 136 | K27: 158.31
A28: Profit before tax | B28: 1839.3 | C28: 2428.95 | D28: 2673.49 | E28: 2812.79 | F28: 2857.32 | G28: 3255.97 | H28: 4038.29 | I28: 5288.87 | J28: 4447.47 | K28: 4609.65
A29: Tax | B29: 614.11 | C29: 822.02 | D29: 705.05 | E29: 730.36 | F29: 738.91 | G29: 865.45 | H29: 1039.62 | I29: 1356.03 | J29: 1132.97 | K29: 1065.05
A30: Net profit | B30: 1225.19 | C30: 1606.93 | D30: 1968.44 | E30: 2082.43 | F30: 2118.41 | G30: 2390.52 | H30: 2998.67 | I30: 3932.84 | J30: 3314.5 | K30: 3544.6
A31: Dividend Amount | B31: 829.21 | C31: 1108.83 | D31: 3297.56 | E31: 1928.4 | F31: 1928.4 | G31: 2121.24 | H31: 1677.71 | I31: 3104.72 | J31: 2603.34 | K31: 2313.96
A40: Quarters
A41: Report Date | B41: 45382 | C41: 45473 | D41: 45565 | E41: 45657 | F41: 45747 | G41: 45838 | H41: 45930 | I41: 46022 | J41: 46112 | K41: 46203
A42: Sales | B42: 5267.59 | C42: 4813.95 | D42: 5104 | E42: 4779.73 | F42: 5503.88 | G42: 5096.16 | H42: 5643.61 | I42: 5667.04 | J42: 6747.79 | K42: 6378.18
A43: Expenses | B43: 3917.54 | C43: 3699.62 | D43: 3936.27 | E43: 3677.04 | F43: 4115.58 | G43: 3996.03 | H43: 4406.97 | I43: 4466.09 | J43: 4976.19 | K43: 4840.05
A44: Other Income | B44: 36.83 | C44: 39.12 | D44: 297.68 | E44: 4.44 | F44: 9.1 | G44: 4.17 | H44: 1.64 | I44: 169.78 | J44: -17.72 | K44: 16.24
A45: Depreciation | B45: 110.1 | C45: 112.71 | D45: 121.6 | E45: 150.27 | F45: 155.34 | G45: 156.94 | H45: 163.35 | I45: 174.41 | J45: 204.53 | K45: 187.8
A46: Interest | B46: 26.2 | C46: 31.68 | D46: 32.22 | E46: 34.6 | F46: 37.5 | G46: 46.89 | H46: 46.41 | I46: 28.25 | J46: 36.76 | K46: 42.18
A47: Profit before tax | B47: 1250.58 | C47: 1009.06 | D47: 1311.59 | E47: 922.26 | F47: 1204.56 | G47: 900.47 | H47: 1028.52 | I47: 1168.07 | J47: 1512.59 | K47: 1324.39
A48: Tax | B48: 316.41 | C48: 262.46 | D48: 325.23 | E48: 226.13 | F48: 319.15 | G48: 241.24 | H48: 275.32 | I48: 150.01 | J48: 398.48 | K48: 349.27
A49: Net profit | B49: 934.17 | C49: 746.6 | D49: 986.36 | E49: 696.13 | F49: 885.41 | G49: 659.23 | H49: 753.2 | I49: 1018.06 | J49: 1114.11 | K49: 975.12
A50: Operating Profit | B50: 1350.05 | C50: 1114.33 | D50: 1167.73 | E50: 1102.69 | F50: 1388.3 | G50: 1100.13 | H50: 1236.64 | I50: 1200.95 | J50: 1771.6 | K50: 1538.13
A55: BALANCE SHEET
A56: Report Date | B56: 43100 | C56: 43465 | D56: 43830 | E56: 44196 | F56: 44561 | G56: 44926 | H56: 45291 | I56: 45382 | J56: 45747 | K56: 46112
A57: Equity Share Capital | B57: 96.42 | C57: 96.42 | D57: 96.42 | E57: 96.42 | F57: 96.42 | G57: 96.42 | H57: 96.42 | I57: 96.42 | J57: 96.42 | K57: 192.83
A58: Reserves | B58: 3324.17 | C58: 3577.32 | D58: 1822.45 | E58: 1922.92 | F58: 1849.96 | G58: 2362.75 | H58: 2362.75 | I58: 3244.47 | J58: 4020.73 | K58: 5116.41
A59: Borrowings | B59: 35.14 | C59: 35.14 | D59: 188.94 | E59: 147.49 | F59: 266.46 | G59: 270.52 | H59: 270.52 | I59: 344.53 | J59: 1166.85 | K59: 444.16
A60: Other Liabilities | B60: 3906.86 | C60: 4379.2 | D60: 5065.13 | E60: 5732.9 | F60: 6021.29 | G60: 6249.05 | H60: 6249.05 | I60: 6837.64 | J60: 7039.89 | K60: 7603.77
A61: Total | B61: 7362.59 | C61: 8088.08 | D61: 7172.94 | E61: 7899.73 | F61: 8234.13 | G61: 8978.74 | H61: 8978.74 | I61: 10523.06 | J61: 12323.89 | K61: 13357.17
A62: Net Block | B62: 2616.18 | C62: 2400.62 | D62: 2341.45 | E62: 2179.41 | F62: 2994.67 | G62: 3043.7 | H62: 3043.7 | I62: 3460.25 | J62: 5473.61 | K62: 6290.42
A63: Capital Work in Progress | B63: 94.16 | C63: 105.2 | D63: 143.3 | E63: 638.58 | F63: 246.23 | G63: 358.36 | H63: 358.36 | I63: 1741.71 | J63: 1172.56 | K63: 506.98
A64: Investments | B64: 1978.87 | C64: 2658.49 | D64: 1751.05 | E64: 1463.77 | F64: 773.98 | G64: 777.54 | H64: 777.54 | I64: 463.87 | J64: 705.6 | K64: 705.6
A65: Other Assets | B65: 2673.38 | C65: 2923.77 | D65: 2937.14 | E65: 3617.97 | F65: 4219.25 | G65: 4799.14 | H65: 4799.14 | I65: 4857.23 | J65: 4972.12 | K65: 5854.17
A66: Total | B66: 7362.59 | C66: 8088.08 | D66: 7172.94 | E66: 7899.73 | F66: 8234.13 | G66: 8978.74 | H66: 8978.74 | I66: 10523.06 | J66: 12323.89 | K66: 13357.17
A67: Receivables | B67: 88.97 | C67: 124.59 | D67: 124.33 | E67: 164.93 | F67: 165.97 | G67: 191.89 | H67: 191.89 | I67: 300.46 | J67: 363.15 | K67: 329.47
... A69: Cash & Bank | B69: 1457.42 | C69: 1610.06 | D69: 1308.05 | E69: 1769.87 | F69: 735.41 | G69: 945.55 | H69: 945.55 | I69: 778.85 | J69: 95.65 | K69: 1340.87
A70: No. of Equity Shares | B70: 96415716 | C70: 96415716 | D70: 96415716 | E70: 96415716 | F70: 96415716 | G70: 96415716 | I70: 964157160 | J70: 964157160 | K70: 1928314320
A71: New Bonus Shares
A72: Face value | B72: 10 | C72: 10 | D72: 10 | E72: 10 | F72: 10 | G72: 10 | H72: 10 | I72: 1 | J72: 1 | K72: 1
A80: CASH FLOW:
A81: Report Date | B81: 43100 | C81: 43465 | D81: 43830 | E81: 44196 | F81: 44561 | G81: 44926 | H81: 45291 | I81: 45382 | J81: 45747 | K81: 46112
A82: Cash from Operating Activity | B82: 1817.79 | C82: 2052.45 | D82: 2295.25 | E82: 2454.48 | F82: 2236 | G82: 2737.43 | H82: 3392.19 | I82: 4174.79 | J82: 2934.53 | K82: 5047.56
A83: Cash from Investing Activity | B83: -130.56 | C83: -52.41 | D83: 82.99 | E83: -321.46 | F83: -1920.33 | G83: -391.73 | H83: -926.99 | I83: -1237.42 | J83: -1810.9 | K83: -623.68
A84: Cash from Financing Activity | B84: -996.62 | C84: -1317.42 | D84: -3601.53 | E84: -1955.89 | F84: -2019.97 | G84: -2122.74 | H84: -2436.47 | I84: -3134.92 | J84: -1846.3 | K84: -3179.49
A85: Net Cash Flow | B85: 690.61 | C85: 682.62 | D85: -1223.29 | E85: 177.13 | F85: -1704.3 | G85: 222.96 | H85: 28.73 | I85: -197.55 | J85: -722.67 | K85: 1244.39
A90: PRICE: | B90: 393.55 | C90: 554.24 | D90: 739.27 | E90: 919.51 | F90: 985.29 | G90: 980.3 | H90: 1329.02 | I90: 1311.18 | J90: 1125.38 | K90: 1174.8
A92: DERIVED:
A93: Adjusted Equity Shares in Cr | B93: 192.8 | C93: 192.8 | D93: 192.8 | E93: 192.8 | F93: 192.8 | G93: 192.8 | H93: 192.8 | I93: 192.83 | J93: 192.83 | K93: 192.83

Sheet Profit & Loss
A1: ='Data Sheet'!B1 -> NESTLE INDIA LTD | H1: =UPDATE
A3: Narration | B3: ='Data Sheet'!B16 -> 43100 | C3: ='Data Sheet'!C16 -> 43465 | D3: ='Data Sheet'!D16 -> 43830 | E3: ='Data Sheet'!E16 -> 44196 | F3: ='Data Sheet'!F16 -> 44561 | G3: ='Data Sheet'!G16 -> 44926 | H3: ='Data Sheet'!H16 -> 45291 | I3: ='Data Sheet'!I16 -> 45382 | ... K3: ='Data Sheet'!K16 -> 46112
A4: Sales | B4: ='Data Sheet'!B17 -> 10009.6 | C4: ='Data Sheet'!C17 -> 11292.27 | D4: ='Data Sheet'!D17 -> 12368.9 | E4: ='Data Sheet'!E17 -> 13350.03 | F4: ='Data Sheet'!F17 -> 14740.59 | G4: ='Data Sheet'!G17 -> 16896.96 | H4: ='Data Sheet'!H17 -> 19126.3 | I4: ='Data Sheet'!I17 -> 24393.89 | ... K4: ='Data Sheet'!K17 -> 23154.6
A5: Expenses | B5: =SUM('Data Sheet'!B18,'Data Sheet'!B20:B24, -1*'Data Sheet'!B19) -> 7913.07 | C5: =SUM('Data Sheet'!C18,'Data Sheet'!C20:C24, -1*'Data Sheet'!C19) -> 8674.62 | D5: =SUM('Data Sheet'!D18,'Data Sheet'!D20:D24, -1*'Data Sheet'!D19) -> 9443.02 | E5: =SUM('Data Sheet'!E18,'Data Sheet'!E20:E24, -1*'Data Sheet'!E19) -> 10148.53 | F5: =SUM('Data Sheet'!F18,'Data Sheet'!F20:F24, -1*'Data Sheet'!F19) -> 11178.19 | G5: =SUM('Data Sheet'!G18,'Data Sheet'!G20:G24, -1*'Data Sheet'!G19) -> 13190.67 | H5: =SUM('Data Sheet'!H18,'Data Sheet'!H20:H24, -1*'Data Sheet'!H19) -> 14655.31 | I5: =SUM('Data Sheet'!I18,'Data Sheet'!I20:I24, -1*'Data Sheet'!I19) -> 18550.77 | ... K5: =SUM('Data Sheet'!K18,'Data Sheet'!K20:K24, -1*'Data Sheet'!K19) -> 17847.64
A6: Operating Profit | B6: =B4-B5 -> 2096.53 | C6: =C4-C5 -> 2617.65 | D6: =D4-D5 -> 2925.88 | E6: =E4-E5 -> 3201.5 | F6: =F4-F5 -> 3562.4 | G6: =G4-G5 -> 3706.29 | H6: =H4-H5 -> 4470.99 | I6: =I4-I5 -> 5843.12 | ... K6: =K4-K5 -> 5306.96
A7: Other Income | B7: ='Data Sheet'!B25 -> 176.92 | C7: ='Data Sheet'!C25 -> 258.92 | D7: ='Data Sheet'!D25 -> 246.88 | E7: ='Data Sheet'!E25 -> 145.85 | F7: ='Data Sheet'!F25 -> -112.38 | G7: ='Data Sheet'!G25 -> 107.26 | H7: ='Data Sheet'!H25 -> 115.5 | I7: ='Data Sheet'!I25 -> 158.99 | ... K7: ='Data Sheet'!K25 -> 160.23
A8: Depreciation | B8: ='Data Sheet'!B26 -> 342.25 | C8: ='Data Sheet'!C26 -> 335.67 | D8: ='Data Sheet'!D26 -> 370.15 | E8: ='Data Sheet'!E26 -> 370.38 | F8: ='Data Sheet'!F26 -> 391.02 | G8: ='Data Sheet'!G26 -> 403.01 | H8: ='Data Sheet'!H26 -> 428.91 | I8: ='Data Sheet'!I26 -> 567.75 | ... K8: ='Data Sheet'!K26 -> 699.23
A9: Interest | B9: ='Data Sheet'!B27 -> 91.9 | C9: ='Data Sheet'!C27 -> 111.95 | D9: ='Data Sheet'!D27 -> 129.12 | E9: ='Data Sheet'!E27 -> 164.18 | F9: ='Data Sheet'!F27 -> 201.68 | G9: ='Data Sheet'!G27 -> 154.57 | H9: ='Data Sheet'!H27 -> 119.29 | I9: ='Data Sheet'!I27 -> 145.49 | ... K9: ='Data Sheet'!K27 -> 158.31
A10: Profit before tax | B10: ='Data Sheet'!B28 -> 1839.3 | C10: ='Data Sheet'!C28 -> 2428.95 | D10: ='Data Sheet'!D28 -> 2673.49 | E10: ='Data Sheet'!E28 -> 2812.79 | F10: ='Data Sheet'!F28 -> 2857.32 | G10: ='Data Sheet'!G28 -> 3255.97 | H10: ='Data Sheet'!H28 -> 4038.29 | I10: ='Data Sheet'!I28 -> 5288.87 | ... K10: ='Data Sheet'!K28 -> 4609.65
A11: Tax | B11: ='Data Sheet'!B29 -> 614.11 | C11: ='Data Sheet'!C29 -> 822.02 | D11: ='Data Sheet'!D29 -> 705.05 | E11: ='Data Sheet'!E29 -> 730.36 | F11: ='Data Sheet'!F29 -> 738.91 | G11: ='Data Sheet'!G29 -> 865.45 | H11: ='Data Sheet'!H29 -> 1039.62 | I11: ='Data Sheet'!I29 -> 1356.03 | ... K11: ='Data Sheet'!K29 -> 1065.05
A12: Net profit | B12: ='Data Sheet'!B30 -> 1225.19 | C12: ='Data Sheet'!C30 -> 1606.93 | D12: ='Data Sheet'!D30 -> 1968.44 | E12: ='Data Sheet'!E30 -> 2082.43 | F12: ='Data Sheet'!F30 -> 2118.41 | G12: ='Data Sheet'!G30 -> 2390.52 | H12: ='Data Sheet'!H30 -> 2998.67 | I12: ='Data Sheet'!I30 -> 3932.84 | ... K12: ='Data Sheet'!K30 -> 3544.6
A13: EPS | B13: =IF('Data Sheet'!B93>0,B12/'Data Sheet'!B93,0) -> 6.3547199 | C13: =IF('Data Sheet'!C93>0,C12/'Data Sheet'!C93,0) -> 8.3346992 | D13: =IF('Data Sheet'!D93>0,D12/'Data Sheet'!D93,0) -> 10.209751 | E13: =IF('Data Sheet'!E93>0,E12/'Data Sheet'!E93,0) -> 10.800985 | F13: =IF('Data Sheet'!F93>0,F12/'Data Sheet'!F93,0) -> 10.987604 | G13: =IF('Data Sheet'!G93>0,G12/'Data Sheet'!G93,0) -> 12.398963 | H13: =IF('Data Sheet'!H93>0,H12/'Data Sheet'!H93,0) -> 15.553268 | I13: =IF('Data Sheet'!I93>0,I12/'Data Sheet'!I93,0) -> 20.395374 | ... K13: =IF('Data Sheet'!K93>0,K12/'Data Sheet'!K93,0) -> 18.381995
A14: Price to earning | B14: =IF(B15>0,B15/B13,"") -> 61.930345 | C14: =IF(C15>0,C15/C13,"") -> 66.497901 | D14: =IF(D15>0,D15/D13,"") -> 72.40823 | E14: =IF(E15>0,E15/E13,"") -> 85.132047 | F14: =IF(F15>0,F15/F13,"") -> 89.672874 | G14: =IF(G15>0,G15/G13,"") -> 79.063066 | H14: =IF(H15>0,H15/H13,"") -> 85.449568 | I14: =IF(I15>0,I15/I13,"") -> 64.288107 | ... K14: =IF(K15>0,K15/K13,"") -> 63.910366
A15: Price | B15: ='Data Sheet'!B90 -> 393.55 | C15: ='Data Sheet'!C90 -> 554.24 | D15: ='Data Sheet'!D90 -> 739.27 | E15: ='Data Sheet'!E90 -> 919.51 | F15: ='Data Sheet'!F90 -> 985.29 | G15: ='Data Sheet'!G90 -> 980.3 | H15: ='Data Sheet'!H90 -> 1329.02 | I15: ='Data Sheet'!I90 -> 1311.18 | ... K15: ='Data Sheet'!K90 -> 1174.8
A17: RATIOS:
A18: Dividend Payout | B18: =IF('Data Sheet'!B30>0, 'Data Sheet'!B31/'Data Sheet'!B30, 0) -> 0.67680115 | C18: =IF('Data Sheet'!C30>0, 'Data Sheet'!C31/'Data Sheet'!C30, 0) -> 0.69003006 | D18: =IF('Data Sheet'!D30>0, 'Data Sheet'!D31/'Data Sheet'!D30, 0) -> 1.6752149 | E18: =IF('Data Sheet'!E30>0, 'Data Sheet'!E31/'Data Sheet'!E30, 0) -> 0.92603353 | F18: =IF('Data Sheet'!F30>0, 'Data Sheet'!F31/'Data Sheet'!F30, 0) -> 0.91030537 | G18: =IF('Data Sheet'!G30>0, 'Data Sheet'!G31/'Data Sheet'!G30, 0) -> 0.88735505 | H18: =IF('Data Sheet'!H30>0, 'Data Sheet'!H31/'Data Sheet'!H30, 0) -> 0.5594847 | I18: =IF('Data Sheet'!I30>0, 'Data Sheet'!I31/'Data Sheet'!I30, 0) -> 0.78943461 | ... K18: =IF('Data Sheet'!K30>0, 'Data Sheet'!K31/'Data Sheet'!K30, 0) -> 0.65281273
A19: OPM | B19: =IF(B6>0,B6/B4,0) -> 0.20945193 | C19: =IF(C6>0,C6/C4,0) -> 0.23180902 | D19: =IF(D6>0,D6/D4,0) -> 0.23655135 | E19: =IF(E6>0,E6/E4,0) -> 0.2398122 | F19: =IF(F6>0,F6/F4,0) -> 0.24167282 | G19: =IF(G6>0,G6/G4,0) -> 0.21934656 | H19: =IF(H6>0,H6/H4,0) -> 0.23376137 | I19: =IF(I6>0,I6/I4,0) -> 0.23953211 | ... K19: =IF(K6>0,K6/K4,0) -> 0.22919679

Sheet Balance Sheet
A1: ='Profit & Loss'!A1 -> NESTLE INDIA LTD | E1: =UPDATE | J1: SCREENER.IN
A3: Narration | B3: ='Data Sheet'!B56 -> 43100 | C3: ='Data Sheet'!C56 -> 43465 | D3: ='Data Sheet'!D56 -> 43830 | E3: ='Data Sheet'!E56 -> 44196 | F3: ='Data Sheet'!F56 -> 44561 | G3: ='Data Sheet'!G56 -> 44926 | H3: ='Data Sheet'!H56 -> 45291 | I3: ='Data Sheet'!I56 -> 45382 | ... K3: ='Data Sheet'!K56 -> 46112
A4: Equity Share Capital | B4: ='Data Sheet'!B57 -> 96.42 | C4: ='Data Sheet'!C57 -> 96.42 | D4: ='Data Sheet'!D57 -> 96.42 | E4: ='Data Sheet'!E57 -> 96.42 | F4: ='Data Sheet'!F57 -> 96.42 | G4: ='Data Sheet'!G57 -> 96.42 | H4: ='Data Sheet'!H57 -> 96.42 | I4: ='Data Sheet'!I57 -> 96.42 | ... K4: ='Data Sheet'!K57 -> 192.83
A5: Reserves | B5: ='Data Sheet'!B58 -> 3324.17 | C5: ='Data Sheet'!C58 -> 3577.32 | D5: ='Data Sheet'!D58 -> 1822.45 | E5: ='Data Sheet'!E58 -> 1922.92 | F5: ='Data Sheet'!F58 -> 1849.96 | G5: ='Data Sheet'!G58 -> 2362.75 | H5: ='Data Sheet'!H58 -> 2362.75 | I5: ='Data Sheet'!I58 -> 3244.47 | ... K5: ='Data Sheet'!K58 -> 5116.41
A6: Borrowings | B6: ='Data Sheet'!B59 -> 35.14 | C6: ='Data Sheet'!C59 -> 35.14 | D6: ='Data Sheet'!D59 -> 188.94 | E6: ='Data Sheet'!E59 -> 147.49 | F6: ='Data Sheet'!F59 -> 266.46 | G6: ='Data Sheet'!G59 -> 270.52 | H6: ='Data Sheet'!H59 -> 270.52 | I6: ='Data Sheet'!I59 -> 344.53 | ... K6: ='Data Sheet'!K59 -> 444.16
A7: Other Liabilities | B7: ='Data Sheet'!B60 -> 3906.86 | C7: ='Data Sheet'!C60 -> 4379.2 | D7: ='Data Sheet'!D60 -> 5065.13 | E7: ='Data Sheet'!E60 -> 5732.9 | F7: ='Data Sheet'!F60 -> 6021.29 | G7: ='Data Sheet'!G60 -> 6249.05 | H7: ='Data Sheet'!H60 -> 6249.05 | I7: ='Data Sheet'!I60 -> 6837.64 | ... K7: ='Data Sheet'!K60 -> 7603.77
A8: Total | B8: ='Data Sheet'!B61 -> 7362.59 | C8: ='Data Sheet'!C61 -> 8088.08 | D8: ='Data Sheet'!D61 -> 7172.94 | E8: ='Data Sheet'!E61 -> 7899.73 | F8: ='Data Sheet'!F61 -> 8234.13 | G8: ='Data Sheet'!G61 -> 8978.74 | H8: ='Data Sheet'!H61 -> 8978.74 | I8: ='Data Sheet'!I61 -> 10523.06 | ... K8: ='Data Sheet'!K61 -> 13357.17
A10: Net Block | B10: ='Data Sheet'!B62 -> 2616.18 | C10: ='Data Sheet'!C62 -> 2400.62 | D10: ='Data Sheet'!D62 -> 2341.45 | E10: ='Data Sheet'!E62 -> 2179.41 | F10: ='Data Sheet'!F62 -> 2994.67 | G10: ='Data Sheet'!G62 -> 3043.7 | H10: ='Data Sheet'!H62 -> 3043.7 | I10: ='Data Sheet'!I62 -> 3460.25 | ... K10: ='Data Sheet'!K62 -> 6290.42
A11: Capital Work in Progress | B11: ='Data Sheet'!B63 -> 94.16 | C11: ='Data Sheet'!C63 -> 105.2 | D11: ='Data Sheet'!D63 -> 143.3 | E11: ='Data Sheet'!E63 -> 638.58 | F11: ='Data Sheet'!F63 -> 246.23 | G11: ='Data Sheet'!G63 -> 358.36 | H11: ='Data Sheet'!H63 -> 358.36 | I11: ='Data Sheet'!I63 -> 1741.71 | ... K11: ='Data Sheet'!K63 -> 506.98
A12: Investments | B12: ='Data Sheet'!B64 -> 1978.87 | C12: ='Data Sheet'!C64 -> 2658.49 | D12: ='Data Sheet'!D64 -> 1751.05 | E12: ='Data Sheet'!E64 -> 1463.77 | F12: ='Data Sheet'!F64 -> 773.98 | G12: ='Data Sheet'!G64 -> 777.54 | H12: ='Data Sheet'!H64 -> 777.54 | I12: ='Data Sheet'!I64 -> 463.87 | ... K12: ='Data Sheet'!K64 -> 705.6
A13: Other Assets | B13: ='Data Sheet'!B65 -> 2673.38 | C13: ='Data Sheet'!C65 -> 2923.77 | D13: ='Data Sheet'!D65 -> 2937.14 | E13: ='Data Sheet'!E65 -> 3617.97 | F13: ='Data Sheet'!F65 -> 4219.25 | G13: ='Data Sheet'!G65 -> 4799.14 | H13: ='Data Sheet'!H65 -> 4799.14 | I13: ='Data Sheet'!I65 -> 4857.23 | ... K13: ='Data Sheet'!K65 -> 5854.17
A14: Total | B14: ='Data Sheet'!B66 -> 7362.59 | C14: ='Data Sheet'!C66 -> 8088.08 | D14: ='Data Sheet'!D66 -> 7172.94 | E14: ='Data Sheet'!E66 -> 7899.73 | F14: ='Data Sheet'!F66 -> 8234.13 | G14: ='Data Sheet'!G66 -> 8978.74 | H14: ='Data Sheet'!H66 -> 8978.74 | I14: ='Data Sheet'!I66 -> 10523.06 | ... K14: ='Data Sheet'!K66 -> 13357.17
A16: Working Capital | B16: =B13-B7 -> -1233.48 | C16: =C13-C7 -> -1455.43 | D16: =D13-D7 -> -2127.99 | E16: =E13-E7 -> -2114.93 | F16: =F13-F7 -> -1802.04 | G16: =G13-G7 -> -1449.91 | H16: =H13-H7 -> -1449.91 | I16: =I13-I7 -> -1980.41 | ... K16: =K13-K7 -> -1749.6
A17: Debtors | B17: ='Data Sheet'!B67 -> 88.97 | C17: ='Data Sheet'!C67 -> 124.59 | D17: ='Data Sheet'!D67 -> 124.33 | E17: ='Data Sheet'!E67 -> 164.93 | F17: ='Data Sheet'!F67 -> 165.97 | G17: ='Data Sheet'!G67 -> 191.89 | H17: ='Data Sheet'!H67 -> 191.89 | I17: ='Data Sheet'!I67 -> 300.46 | ... K17: ='Data Sheet'!K67 -> 329.47
A18: Inventory | B18: ='Data Sheet'!B68 -> 902.47 | C18: ='Data Sheet'!C68 -> 965.55 | D18: ='Data Sheet'!D68 -> 1283.07 | E18: ='Data Sheet'!E68 -> 1416.48 | F18: ='Data Sheet'!F68 -> 1592.65 | G18: ='Data Sheet'!G68 -> 1928.77 | H18: ='Data Sheet'!H68 -> 1928.77 | I18: ='Data Sheet'!I68 -> 2089.36 | ... K18: ='Data Sheet'!K68 -> 2569.22
A20: Debtor Days | B20: =IF('Profit & Loss'!B4>0,'Balance Sheet'!B17/('Profit & Loss'!B4/365),0) -> 3.2442905 | C20: =IF('Profit & Loss'!C4>0,'Balance Sheet'!C17/('Profit & Loss'!C4/365),0) -> 4.0271221 | D20: =IF('Profit & Loss'!D4>0,'Balance Sheet'!D17/('Profit & Loss'!D4/365),0) -> 3.6689156 | E20: =IF('Profit & Loss'!E4>0,'Balance Sheet'!E17/('Profit & Loss'!E4/365),0) -> 4.509312 | F20: =IF('Profit & Loss'!F4>0,'Balance Sheet'!F17/('Profit & Loss'!F4/365),0) -> 4.1096761 | G20: =IF('Profit & Loss'!G4>0,'Balance Sheet'!G17/('Profit & Loss'!G4/365),0) -> 4.1451155 | H20: =IF('Profit & Loss'!H4>0,'Balance Sheet'!H17/('Profit & Loss'!H4/365),0) -> 3.6619655 | I20: =IF('Profit & Loss'!I4>0,'Balance Sheet'!I17/('Profit & Loss'!I4/365),0) -> 4.4957118 | ... K20: =IF('Profit & Loss'!K4>0,'Balance Sheet'!K17/('Profit & Loss'!K4/365),0) -> 5.1936354
A21: Inventory Turnover | B21: =IF('Balance Sheet'!B18>0,'Profit & Loss'!B4/'Balance Sheet'!B18,0) -> 11.091338 | C21: =IF('Balance Sheet'!C18>0,'Profit & Loss'!C4/'Balance Sheet'!C18,0) -> 11.695169 | D21: =IF('Balance Sheet'!D18>0,'Profit & Loss'!D4/'Balance Sheet'!D18,0) -> 9.640082 | E21: =IF('Balance Sheet'!E18>0,'Profit & Loss'!E4/'Balance Sheet'!E18,0) -> 9.4247924 | F21: =IF('Balance Sheet'!F18>0,'Profit & Loss'!F4/'Balance Sheet'!F18,0) -> 9.2553857 | G21: =IF('Balance Sheet'!G18>0,'Profit & Loss'!G4/'Balance Sheet'!G18,0) -> 8.7604847 | H21: =IF('Balance Sheet'!H18>0,'Profit & Loss'!H4/'Balance Sheet'!H18,0) -> 9.9163197 | I21: =IF('Balance Sheet'!I18>0,'Profit & Loss'!I4/'Balance Sheet'!I18,0) -> 11.675293 | ... K21: =IF('Balance Sheet'!K18>0,'Profit & Loss'!K4/'Balance Sheet'!K18,0) -> 9.0123072
A23: Return on Equity | B23: =IF(SUM('Balance Sheet'!B4:B5)>0,'Profit & Loss'!B12/SUM('Balance Sheet'!B4:B5),"") -> 0.3581809 | C23: =IF(SUM('Balance Sheet'!C4:C5)>0,'Profit & Loss'!C12/SUM('Balance Sheet'!C4:C5),"") -> 0.43740983 | D23: =IF(SUM('Balance Sheet'!D4:D5)>0,'Profit & Loss'!D12/SUM('Balance Sheet'!D4:D5),"") -> 1.0258329 | E23: =IF(SUM('Balance Sheet'!E4:E5)>0,'Profit & Loss'!E12/SUM('Balance Sheet'!E4:E5),"") -> 1.0312429 | F23: =IF(SUM('Balance Sheet'!F4:F5)>0,'Profit & Loss'!F12/SUM('Balance Sheet'!F4:F5),"") -> 1.0883846 | G23: =IF(SUM('Balance Sheet'!G4:G5)>0,'Profit & Loss'!G12/SUM('Balance Sheet'!G4:G5),"") -> 0.97208408 | H23: =IF(SUM('Balance Sheet'!H4:H5)>0,'Profit & Loss'!H12/SUM('Balance Sheet'!H4:H5),"") -> 1.219383 | I23: =IF(SUM('Balance Sheet'!I4:I5)>0,'Profit & Loss'!I12/SUM('Balance Sheet'!I4:I5),"") -> 1.1771833 | ... K23: =IF(SUM('Balance Sheet'!K4:K5)>0,'Profit & Loss'!K12/SUM('Balance Sheet'!K4:K5),"") -> 0.66762851
A24: Return on Capital Emp | C24: =IF((B4+B5+B6+C4+C5+C6)>0,('Profit & Loss'!C10+'Profit & Loss'!C9)*2/(B4+B5+B6+C4+C5+C6),"") -> 0.70929192 | D24: =IF((C4+C5+C6+D4+D5+D6)>0,('Profit & Loss'!D10+'Profit & Loss'!D9)*2/(C4+C5+C6+D4+D5+D6),"") -> 0.96364427 | E24: =IF((D4+D5+D6+E4+E5+E6)>0,('Profit & Loss'!E10+'Profit & Loss'!E9)*2/(D4+D5+D6+E4+E5+E6),"") -> 1.3928518 | F24: =IF((E4+E5+E6+F4+F5+F6)>0,('Profit & Loss'!F10+'Profit & Loss'!F9)*2/(E4+E5+E6+F4+F5+F6),"") -> 1.3969089 | G24: =IF((F4+F5+F6+G4+G5+G6)>0,('Profit & Loss'!G10+'Profit & Loss'!G9)*2/(F4+F5+F6+G4+G5+G6),"") -> 1.3800786 | H24: =IF((G4+G5+G6+H4+H5+H6)>0,('Profit & Loss'!H10+'Profit & Loss'!H9)*2/(G4+G5+G6+H4+H5+H6),"") -> 1.523096 | I24: =IF((H4+H5+H6+I4+I5+I6)>0,('Profit & Loss'!I10+'Profit & Loss'!I9)*2/(H4+H5+H6+I4+I5+I6),"") -> 1.6942375 | J24: =IF((I4+I5+I6+J4+J5+J6)>0,('Profit & Loss'!J10+'Profit & Loss'!J9)*2/(I4+I5+I6+J4+J5+J6),"") -> 1.0220215 | K24: =IF((J4+J5+J6+K4+K5+K6)>0,('Profit & Loss'!K10+'Profit & Loss'!K9)*2/(J4+J5+J6+K4+K5+K6),"") -> 0.86396434

Sheet Cash Flow Data
C1: 43435 | D1: 43800 | E1: 44166 | F1: 44531 | G1: 44896 | H1: 45261 | I1: 45352 | J1: 45717 | K1: 46082
B2: Cash from Operating Activity - | C2: 2052 | D2: 2295 | E2: 2454 | F2: 2236 | G2: 2737 | H2: 3392 | I2: 4175 | J2: 2935 | K2: 5048
B3: Profit from operations | C3: 2521 | D3: 2805 | E3: 3061 | F3: 3136 | G3: 3609 | H3: 4388 | I3: 5722 | J3: 4672 | K3: 5326
B4: Receivables | C4: -36 | D4: 0 | E4: -42 | F4: -2 | G4: -28 | H4: -11 | I4: -109 | J4: -70 | K4: 34
B5: Inventory | C5: -63 | D5: -318 | E5: -133 | F5: -169 | G5: -336 | H5: 56 | I5: -161 | J5: -767 | K5: 281
B6: Payables | C6: 257 | D6: 253 | E6: 23 | F6: 217 | G6: 178 | H6: 68 | I6: 310 | J6: 134 | K6: 588
B7: Loans Advances | C7: 0 | D7: 0 | E7: 0 | F7: -40 | G7: -30 | H7: -30 | I7: -21 | J7: -199 | K7: -73
B8: Operating borrowings | C8: 0 | D8: 0 | E8: 0 | F8: 0 | G8: 0 | H8: 0 | I8: 0 | J8: 0 | K8: 0
B9: Other WC items | C9: 255 | D9: 227 | E9: 249 | F9: -179 | G9: 185 | H9: -19 | I9: -268 | J9: 155 | K9: -37
B10: Working capital changes | C10: 413 | D10: 163 | E10: 97 | F10: -172 | G10: -30 | H10: 63 | I10: -249 | J10: -747 | K10: 793
B11: Direct taxes | C11: -881 | D11: -673 | E11: -703 | F11: -729 | G11: -841 | H11: -1059 | I11: -1299 | J11: -990 | K11: -1071
B12: Cash from Investing Activity - | C12: -52 | D12: 83 | E12: -321 | F12: -1920 | G12: -392 | H12: -927 | I12: -1237 | J12: -1811 | K12: -624
B13: Fixed assets purchased | C13: -166 | D13: -155 | E13: -478 | F13: -735 | G13: -550 | H13: -1371 | I13: -1883 | J13: -2009 | K13: -830
... B31: CFO/OP | C31: 1.12 | D31: 1.01 | E31: 0.99 | F31: 0.83 | G31: 0.97 | H31: 1 | I31: 0.94 | J31: 0.82 | K31: 1.15
